{
  "analyses": [
    {
      "timeframe": "M5",
      "tendencia": "up",
      "tipo_onda": "impulso",
      "nivel_entrada": 63798.32,
      "nivel_stop": 63558.03,
      "nivel_alvo": 65266.33,
      "correcao_pct": 38.2,
      "observacoes": "Impulso de alta forte e saudável, correção saudável até 38.2/50.0",
      "padroes": [
        "impulso de alta",
        "correção saudável"
      ],
      "qualidade_setup": "alta",
      "data": "04/06/2026 06:34",
      "caption": ""
    },
    {
      "timeframe": "M5",
      "tendencia": "neutral",
      "tipo_onda": "correcao",
      "nivel_entrada": 63554.71,
      "nivel_stop": null,
      "nivel_alvo": null,
      "correcao_pct": 50.0,
      "observacoes": "Possivel ponto de suporte",
      "padroes": [
        "Fibonacci"
      ],
      "qualidade_setup": "media",
      "data": "04/06/2026 07:27",
      "caption": ""
    },
    {
      "timeframe": "M5",
      "tendencia": "down",
      "tipo_onda": "impulso",
      "nivel_entrada": 62400.3,
      "nivel_stop": null,
      "nivel_alvo": null,
      "correcao_pct": 50.0,
      "observacoes": "Possível continuação da tendência de baixa",
      "padroes": [
        "Fibo"
      ],
      "qualidade_setup": "alta",
      "data": "04/06/2026 11:08",
      "caption": ""
    },
    {
      "timeframe": "M5",
      "tendencia": "down",
      "tipo_onda": "correcao",
      "nivel_entrada": 62998.49,
      "nivel_stop": 63311.04,
      "nivel_alvo": 61748.29,
      "correcao_pct": 38.2,
      "observacoes": "Possivel reversão da tendencia",
      "padroes": [
        "Fibonacci"
      ],
      "qualidade_setup": "media",
      "data": "04/06/2026 11:13",
      "caption": ""
    },
    {
      "timeframe": "M5",
      "tendencia": "up",
      "tipo_onda": "impulso",
      "nivel_entrada": 63815.92,
      "nivel_stop": 63400.0,
      "nivel_alvo": 64500.0,
      "correcao_pct": 50.0,
      "observacoes": "Possível continuação da tendência de alta",
      "padroes": [
        "Ruptura de linha de tendência de baixa"
      ],
      "qualidade_setup": "alta",
      "data": "04/06/2026 12:49"
    },
    {
      "timeframe": "M15",
      "tendencia": "down",
      "tipo_onda": "correcao",
      "nivel_entrada": 62800.0,
      "nivel_stop": 62514.7,
      "nivel_alvo": 63902.4,
      "correcao_pct": 0.05,
      "observacoes": "Possivel reversao da tendencia",
      "padroes": [
        "linha de tendencia"
      ],
      "qualidade_setup": "media",
      "data": "04/06/2026 12:50"
    },
    {
      "timeframe": "M15",
      "tendencia": "up",
      "tipo_onda": "impulso",
      "nivel_entrada": 0.0,
      "nivel_stop": 0.0,
      "nivel_alvo": 0.0,
      "correcao_pct": 0.0,
      "observacoes": "Possivel reversao de tendencia",
      "padroes": [
        "Fundo Duplo"
      ],
      "qualidade_setup": "media",
      "data": "04/06/2026 13:04"
    },
    {
      "timeframe": "15m",
      "tendencia": "neutral",
      "tipo_onda": "",
      "nivel_entrada": 0,
      "nivel_stop": 0,
      "nivel_alvo": 0,
      "correcao_pct": 0,
      "observacoes": "",
      "padroes": [],
      "qualidade_setup": "baixa",
      "data": "05/06/2026 12:50"
    },
    {
      "timeframe": "30m",
      "tendencia": "up",
      "tipo_onda": "impulso",
      "nivel_entrada": 61820.4,
      "nivel_stop": 60720.3,
      "nivel_alvo": 64599.0,
      "correcao_pct": 2.32,
      "observacoes": "Possível continuação de tendência de alta após rompimento da linha de resistência.",
      "padroes": [
        "Triângulo Ascendente"
      ],
      "qualidade_setup": "alta",
      "data": "07/06/2026 11:55"
    },
    {
      "timeframe": "30m",
      "tendencia": "up",
      "tipo_onda": "",
      "nivel_entrada": 1.14946,
      "nivel_stop": 1.14993,
      "nivel_alvo": 1.1644,
      "correcao_pct": 0,
      "observacoes": "",
      "padroes": [],
      "qualidade_setup": "alta",
      "data": "08/06/2026 14:29"
    },
    {
      "timeframe": "curto prazo",
      "tendencia": "up",
      "tipo_onda": "impulso",
      "nivel_entrada": 63542.6,
      "nivel_stop": 59130.0,
      "nivel_alvo": 66954.6,
      "correcao_pct": 0.07,
      "observacoes": "Tendencia de alta com suporte em 59130.0 e resistencia em 66954.6",
      "padroes": [
        "reversão de tendencia",
        "continuação de alta"
      ],
      "qualidade_setup": "alta",
      "data": "08/06/2026 14:29"
    },
    {
      "timeframe": "30m",
      "tendencia": "up",
      "tipo_onda": "impulso",
      "nivel_entrada": 1.15358,
      "nivel_stop": 1.14993,
      "nivel_alvo": 1.16447,
      "correcao_pct": 0.5,
      "observacoes": "Possível continuação de alta após rompimento da resistência em 1.15348",
      "padroes": [
        "Rompimento de resistência",
        "Possível onda impulsiva"
      ],
      "qualidade_setup": "alta",
      "data": "08/06/2026 18:47"
    },
    {
      "timeframe": "15m",
      "tendencia": "down",
      "tipo_onda": "impulso",
      "nivel_entrada": 0.6482,
      "nivel_stop": 0.6325,
      "nivel_alvo": 0.6542,
      "correcao_pct": 2.89,
      "observacoes": "O preço está em uma tendência de baixa, com uma queda recente. O suporte mais próximo está em 0.6325.",
      "padroes": [
        "tendência de baixa",
        "queda recente"
      ],
      "qualidade_setup": "baixa",
      "data": "10/06/2026 10:26"
    },
    {
      "timeframe": "1h",
      "tendencia": "up",
      "tipo_onda": "impulso",
      "nivel_entrada": 61200,
      "nivel_stop": 60500,
      "nivel_alvo": 65000,
      "correcao_pct": 2.5,
      "observacoes": "Possível continuação da tendência de alta após rompimento da resistência",
      "padroes": [
        "Rompimento de resistência",
        "Formação de fundo"
      ],
      "qualidade_setup": "alta",
      "data": "10/06/2026 20:16"
    },
    {
      "timeframe": "1h",
      "tendencia": "up",
      "tipo_onda": "impulso",
      "nivel_entrada": 1.15382,
      "nivel_stop": 1.14993,
      "nivel_alvo": 1.16439,
      "correcao_pct": 0.5,
      "observacoes": "Possível continuação de alta após rompimento da resistência",
      "padroes": [
        "Rompimento de resistência",
        "Formação de fundo"
      ],
      "qualidade_setup": "alta",
      "data": "11/06/2026 05:41"
    },
    {
      "timeframe": "1h",
      "tendencia": "up",
      "tipo_onda": "impulso",
      "nivel_entrada": 61200,
      "nivel_stop": 60500,
      "nivel_alvo": 65000,
      "correcao_pct": 2.5,
      "observacoes": "Possível continuação da tendência de alta após rompimento da resistência",
      "padroes": [
        "Rompimento de resistência",
        "Formação de fundo"
      ],
      "qualidade_setup": "alta",
      "data": "11/06/2026 05:52"
    },
    {
      "timeframe": "M5",
      "tendencia": "down",
      "tipo_onda": "impulsiva",
      "nivel_entrada": 62493.0,
      "nivel_stop": 63250.0,
      "nivel_alvo": 61700.0,
      "correcao_pct": 2.5,
      "observacoes": "Onda de baixa após resistência em 63,250",
      "padroes": [
        "Topo duplo"
      ],
      "qualidade_setup": "alta",
      "data": "11/06/2026 11:21"
    },
    {
      "timeframe": "5m",
      "tendencia": "down",
      "tipo_onda": "",
      "nivel_entrada": 63266.9,
      "nivel_stop": 63266.9,
      "nivel_alvo": 62498.0,
      "correcao_pct": 0,
      "observacoes": "O preco atingiu um pico e iniciou uma tendencia de baixa.",
      "padroes": [],
      "qualidade_setup": "alta",
      "data": "11/06/2026 12:30"
    },
    {
      "timeframe": "5m",
      "tendencia": "up",
      "tipo_onda": "impulso",
      "nivel_entrada": 63522.2,
      "nivel_stop": 63141.8,
      "nivel_alvo": 64800,
      "correcao_pct": 2.5,
      "observacoes": "Possível continuação da tendência de alta após rompimento da resistência",
      "padroes": [
        "Rompimento de resistência",
        "Formação de fundo"
      ],
      "qualidade_setup": "alta",
      "data": "11/06/2026 18:47"
    },
    {
      "timeframe": "5m",
      "tendencia": "up",
      "tipo_onda": "",
      "nivel_entrada": 63661.6,
      "nivel_stop": 63400,
      "nivel_alvo": 63942.7,
      "correcao_pct": 0,
      "observacoes": "Possível continuação de alta após rompimento da resistência",
      "padroes": [
        "Rompimento de resistência",
        "Possível continuação de alta"
      ],
      "qualidade_setup": "alta",
      "data": "11/06/2026 21:46"
    }
  ],
  "signals": [
    {
      "id": 201,
      "symbol": "DOTUSDT",
      "direcao": "down",
      "entrada": 0.9294,
      "stop": 0.9318656999999999,
      "alvo": 0.9220029000000003,
      "risco": 0.002465699999999904,
      "rr": 3.0,
      "data": "10/06/2026 23:14",
      "status": "loss",
      "resultado": "-1R",
      "order_id": null,
      "tipo": "FIGURA_BANDEIRA_BAIXA_M1",
      "figura": "BANDEIRA_BAIXA",
      "fechamento": "11/06/2026 00:34"
    },
    {
      "id": 201,
      "symbol": "LTCUSDT",
      "direcao": "down",
      "entrada": 42.10621,
      "stop": 42.315177014999996,
      "alvo": 41.479308955,
      "risco": 0.20896701499999892,
      "rr": 3.0,
      "data": "10/06/2026 23:27",
      "status": "loss",
      "resultado": "-1R",
      "order_id": null,
      "tipo": "FIGURA_RETANGULO_M1",
      "figura": "RETANGULO",
      "fechamento": "11/06/2026 00:33"
    },
    {
      "id": 201,
      "symbol": "TONUSDT",
      "direcao": "up",
      "entrada": 1.6144,
      "stop": 1.62111015,
      "alvo": 1.63453045,
      "risco": 0.00671014999999997,
      "rr": 3.0,
      "data": "10/06/2026 23:36",
      "status": "loss",
      "resultado": "-1R",
      "order_id": null,
      "tipo": "FIGURA_BANDEIRA_BAIXA_M1",
      "figura": "BANDEIRA_BAIXA",
      "fechamento": "10/06/2026 23:36"
    },
    {
      "id": 201,
      "symbol": "ADAUSDT",
      "direcao": "down",
      "entrada": 0.162183,
      "stop": 0.16264928399999998,
      "alvo": 0.16078414800000004,
      "risco": 0.0004662839999999835,
      "rr": 3.0,
      "data": "10/06/2026 23:46",
      "status": "loss",
      "resultado": "-1R",
      "order_id": null,
      "tipo": "FIGURA_RETANGULO_M1",
      "figura": "RETANGULO",
      "fechamento": "10/06/2026 23:57"
    },
    {
      "id": 201,
      "symbol": "OPUSDT",
      "direcao": "up",
      "entrada": 0.09119,
      "stop": 0.09151573499999999,
      "alvo": 0.09216720499999997,
      "risco": 0.00032573499999999367,
      "rr": 3.0,
      "data": "11/06/2026 00:12",
      "status": "loss",
      "resultado": "-1R",
      "order_id": null,
      "tipo": "FIGURA_BANDEIRA_BAIXA_M1",
      "figura": "BANDEIRA_BAIXA",
      "fechamento": "11/06/2026 00:12"
    },
    {
      "id": 201,
      "symbol": "DOTUSDT",
      "direcao": "down",
      "entrada": 0.9253,
      "stop": 0.9286641,
      "alvo": 0.9152077000000001,
      "risco": 0.003364099999999981,
      "rr": 3.0,
      "data": "11/06/2026 00:16",
      "status": "loss",
      "resultado": "-1R",
      "order_id": null,
      "tipo": "FIGURA_RETANGULO_M1",
      "figura": "RETANGULO",
      "fechamento": "11/06/2026 00:31"
    },
    {
      "id": 201,
      "symbol": "SUIUSDT",
      "direcao": "down",
      "entrada": 0.7519,
      "stop": 0.73653155,
      "alvo": 0.7057946500000001,
      "risco": 0.015368449999999978,
      "rr": 3.0,
      "data": "11/06/2026 01:21",
      "status": "loss",
      "resultado": "-1R",
      "order_id": null,
      "tipo": "TOPO_FUNDO_M5",
      "figura": "",
      "fechamento": "11/06/2026 01:21"
    },
    {
      "id": 201,
      "symbol": "ARBUSDT",
      "direcao": "down",
      "entrada": 0.08014,
      "stop": 0.08054025,
      "alvo": 0.07865,
      "risco": 0.0004002499999999909,
      "rr": 3.7,
      "data": "11/06/2026 01:25",
      "status": "loss",
      "resultado": "-1R",
      "order_id": null,
      "tipo": "FIGURA_RETANGULO_M1",
      "figura": "RETANGULO",
      "fechamento": "11/06/2026 01:40"
    },
    {
      "id": 201,
      "symbol": "TONUSDT",
      "direcao": "up",
      "entrada": 1.6474,
      "stop": 1.6490448599999998,
      "alvo": 1.6523345799999996,
      "risco": 0.0016448599999998592,
      "rr": 3.0,
      "data": "11/06/2026 02:05",
      "status": "loss",
      "resultado": "-1R",
      "order_id": null,
      "tipo": "EW_W2_LONG",
      "fechamento": "11/06/2026 02:06"
    },
    {
      "id": 201,
      "symbol": "SOLUSDT",
      "direcao": "up",
      "entrada": 65.05,
      "stop": 64.94450699999999,
      "alvo": 65.36647900000003,
      "risco": 0.10549300000000983,
      "rr": 3.0,
      "data": "11/06/2026 02:07",
      "status": "loss",
      "resultado": "-1R",
      "order_id": "16b77183-3b0c-405b-ab35-bb2a321e68c2",
      "tipo": "EW_W2_LONG",
      "fechamento": "11/06/2026 03:05"
    },
    {
      "id": 201,
      "symbol": "SOLUSDT",
      "direcao": "up",
      "entrada": 65.12,
      "stop": 65.004465,
      "alvo": 65.46660500000003,
      "risco": 0.11553500000000838,
      "rr": 3.0,
      "data": "11/06/2026 02:20",
      "status": "loss",
      "resultado": "-1R",
      "order_id": null,
      "tipo": "EW_TRI_E_LONG",
      "fechamento": "11/06/2026 03:05"
    },
    {
      "id": 201,
      "symbol": "SUIUSDT",
      "direcao": "up",
      "entrada": 0.7504,
      "stop": 0.749475,
      "alvo": 0.7531749999999998,
      "risco": 0.0009249999999999536,
      "rr": 3.0,
      "data": "11/06/2026 02:35",
      "status": "loss",
      "resultado": "-1R",
      "order_id": null,
      "tipo": "EW_W2_LONG",
      "fechamento": "11/06/2026 03:04"
    },
    {
      "id": 201,
      "symbol": "SOLUSDT",
      "direcao": "up",
      "entrada": 65.08,
      "stop": 65.004465,
      "alvo": 65.306605,
      "risco": 0.07553500000000213,
      "rr": 3.0,
      "data": "11/06/2026 02:51",
      "status": "loss",
      "resultado": "-1R",
      "order_id": null,
      "tipo": "EW_TRI_E_LONG",
      "fechamento": "11/06/2026 03:05"
    },
    {
      "id": 201,
      "symbol": "SOLUSDT",
      "direcao": "up",
      "entrada": 65.02,
      "stop": 65.004465,
      "alvo": 65.066605,
      "risco": 0.015534999999999854,
      "rr": 3.0,
      "data": "11/06/2026 03:01",
      "status": "loss",
      "resultado": "-1R",
      "order_id": null,
      "tipo": "EW_TRI_E_LONG",
      "fechamento": "11/06/2026 03:05"
    },
    {
      "id": 201,
      "symbol": "BNBUSDT",
      "direcao": "down",
      "entrada": 600.17,
      "stop": 600.590119,
      "alvo": 598.909643,
      "risco": 0.4201189999999997,
      "rr": 3.0,
      "data": "11/06/2026 07:14",
      "status": "win",
      "resultado": "+3.0R",
      "order_id": "8d27f361-3e47-4816-be3e-a3e92c7eafcf",
      "tipo": "EW_TRI_E_SHORT",
      "fechamento": "11/06/2026 08:09"
    },
    {
      "id": 201,
      "symbol": "BNBUSDT",
      "direcao": "up",
      "entrada": 601.3,
      "stop": 599.24024,
      "alvo": 607.4792799999999,
      "risco": 2.059759999999983,
      "rr": 3.0,
      "data": "11/06/2026 08:54",
      "status": "loss",
      "resultado": "-1R",
      "order_id": "fc7246af-d9e9-493f-b0b9-c73fe2e4afde",
      "tipo": "M1_SWING_LONG",
      "fechamento": "11/06/2026 09:22"
    },
    {
      "id": 201,
      "symbol": "BNBUSDT",
      "direcao": "up",
      "entrada": 597.75,
      "stop": 597.3315749999999,
      "alvo": 599.0052750000002,
      "risco": 0.4184250000000702,
      "rr": 3.0,
      "data": "11/06/2026 12:20",
      "status": "win",
      "resultado": "+3.0R",
      "order_id": "b5a1212b-d1db-4a58-97e6-e7446b9e7dd3",
      "tipo": "EW_ABC_C_LONG",
      "fechamento": "11/06/2026 12:23"
    },
    {
      "id": 201,
      "symbol": "BNBUSDT",
      "direcao": "down",
      "entrada": 599.57,
      "stop": 602.06102,
      "alvo": 592.0969400000002,
      "risco": 2.491019999999935,
      "rr": 3.0,
      "data": "11/06/2026 12:23",
      "status": "loss",
      "resultado": "-1R",
      "order_id": "6f1a3112-55eb-45d4-90a1-5e954ff371f3",
      "tipo": "M1_SWING_SHORT",
      "fechamento": "11/06/2026 14:44"
    },
    {
      "id": 201,
      "symbol": "BNBUSDT",
      "direcao": "down",
      "entrada": 599.47,
      "stop": 599.989699,
      "alvo": 597.9109030000002,
      "risco": 0.519698999999946,
      "rr": 3.0,
      "data": "11/06/2026 13:22",
      "status": "win",
      "resultado": "+3.0R",
      "order_id": null,
      "tipo": "EW_W2_SHORT",
      "fechamento": "11/06/2026 14:22"
    },
    {
      "id": 201,
      "symbol": "BNBUSDT",
      "direcao": "up",
      "entrada": 598.56,
      "stop": 597.39135,
      "alvo": 602.0659499999998,
      "risco": 1.168649999999957,
      "rr": 3.0,
      "data": "11/06/2026 13:33",
      "status": "loss",
      "resultado": "-1R",
      "order_id": "fbba9a51-c809-4656-8b93-990a50d195ca",
      "tipo": "M1_SWING_LONG",
      "fechamento": "11/06/2026 14:22"
    },
    {
      "id": 201,
      "symbol": "TRXUSDT",
      "direcao": "down",
      "entrada": 0.316689,
      "stop": 0.3212796522,
      "alvo": 0.30291704340000003,
      "risco": 0.004590652199999989,
      "rr": 3.0,
      "data": "11/06/2026 13:35",
      "status": "aberto",
      "resultado": null,
      "order_id": null,
      "tipo": "M1_SWING_SHORT"
    },
    {
      "id": 201,
      "symbol": "TRXUSDT",
      "direcao": "up",
      "entrada": 0.314597,
      "stop": 0.310168787,
      "alvo": 0.32788163900000006,
      "risco": 0.004428213000000014,
      "rr": 3.0,
      "data": "11/06/2026 14:01",
      "status": "aberto",
      "resultado": null,
      "order_id": null,
      "tipo": "M1_SWING_LONG"
    },
    {
      "id": 201,
      "symbol": "LTCUSDT",
      "direcao": "down",
      "entrada": 42.32384,
      "stop": 42.351655421,
      "alvo": 42.240393737,
      "risco": 0.027815420999999674,
      "rr": 3.0,
      "data": "11/06/2026 14:29",
      "status": "loss",
      "resultado": "-1R",
      "order_id": null,
      "tipo": "EW_W2_SHORT",
      "fechamento": "11/06/2026 14:30"
    },
    {
      "id": 201,
      "symbol": "SUIUSDT",
      "direcao": "up",
      "entrada": 0.7614,
      "stop": 0.7456523399999999,
      "alvo": 0.8086429800000001,
      "risco": 0.015747660000000052,
      "rr": 3.0,
      "data": "11/06/2026 15:06",
      "status": "loss",
      "resultado": "-1R",
      "order_id": null,
      "tipo": "M1_SWING_LONG",
      "fechamento": "12/06/2026 03:34"
    },
    {
      "id": 201,
      "symbol": "LTCUSDT",
      "direcao": "up",
      "entrada": 42.54186,
      "stop": 42.066724812,
      "alvo": 43.96726556400001,
      "risco": 0.475135188000003,
      "rr": 3.0,
      "data": "11/06/2026 15:25",
      "status": "aberto",
      "resultado": null,
      "order_id": null,
      "tipo": "M1_SWING_LONG"
    },
    {
      "id": 201,
      "symbol": "SUIUSDT",
      "direcao": "up",
      "entrada": 0.7601,
      "stop": 0.7430539,
      "alvo": 0.8112382999999999,
      "risco": 0.017046099999999953,
      "rr": 3.0,
      "data": "11/06/2026 15:25",
      "status": "aberto",
      "resultado": null,
      "order_id": null,
      "tipo": "M1_SWING_LONG"
    },
    {
      "id": 201,
      "symbol": "BNBUSDT",
      "direcao": "up",
      "entrada": 604.82,
      "stop": 604.3966260000001,
      "alvo": 606.090122,
      "risco": 0.42337399999996705,
      "rr": 3.0,
      "data": "11/06/2026 15:55",
      "status": "loss",
      "resultado": "-1R",
      "order_id": null,
      "tipo": "EW_TRI_E_LONG",
      "fechamento": "11/06/2026 16:08"
    },
    {
      "id": 201,
      "symbol": "ETHUSDT",
      "direcao": "up",
      "entrada": 1684.2,
      "stop": 1680.431136,
      "alvo": 1695.5065920000004,
      "risco": 3.7688640000001215,
      "rr": 3.0,
      "data": "11/06/2026 15:57",
      "status": "loss",
      "resultado": "-1R",
      "order_id": "63de5fb2-213c-42f9-bc30-af19b3e14a8c",
      "tipo": "M1_SWING_LONG",
      "fechamento": "11/06/2026 16:09"
    },
    {
      "id": 201,
      "symbol": "ETHUSDT",
      "direcao": "down",
      "entrada": 1685.83,
      "stop": 1688.9627699999999,
      "alvo": 1676.4316900000001,
      "risco": 3.1327699999999368,
      "rr": 3.0,
      "data": "11/06/2026 15:59",
      "status": "loss",
      "resultado": "-1R",
      "order_id": "7e22544c-4dbc-4901-b74f-70844f24285d",
      "tipo": "M1_SWING_SHORT",
      "fechamento": "11/06/2026 16:34"
    },
    {
      "id": 201,
      "symbol": "SUIUSDT",
      "direcao": "up",
      "entrada": 0.7618,
      "stop": 0.75856863,
      "alvo": 0.7714941100000002,
      "risco": 0.0032313700000000667,
      "rr": 3.0,
      "data": "11/06/2026 16:05",
      "status": "loss",
      "resultado": "-1R",
      "order_id": null,
      "tipo": "EW_W2_LONG",
      "fechamento": "11/06/2026 16:08"
    },
    {
      "id": 201,
      "symbol": "LTCUSDT",
      "direcao": "up",
      "entrada": 42.51484,
      "stop": 42.512080698,
      "alvo": 42.523117906,
      "risco": 0.0027593020000011848,
      "rr": 3.0,
      "data": "11/06/2026 16:13",
      "status": "win",
      "resultado": "+3.0R",
      "order_id": null,
      "tipo": "EW_W2_LONG",
      "fechamento": "11/06/2026 16:14"
    },
    {
      "id": 201,
      "symbol": "ETHUSDT",
      "direcao": "up",
      "entrada": 1681.91,
      "stop": 1677.802714,
      "alvo": 1694.2318580000006,
      "risco": 4.107286000000158,
      "rr": 3.0,
      "data": "11/06/2026 16:27",
      "status": "loss",
      "resultado": "-1R",
      "order_id": "e39e6c14-3e0c-42f4-9895-ac7ec9b2bf2e",
      "tipo": "M1_SWING_LONG",
      "fechamento": "11/06/2026 17:27"
    },
    {
      "id": 201,
      "symbol": "ETHUSDT",
      "direcao": "down",
      "entrada": 1685.49,
      "stop": 1688.9627699999999,
      "alvo": 1675.0716900000004,
      "risco": 3.472769999999855,
      "rr": 3.0,
      "data": "11/06/2026 16:31",
      "status": "loss",
      "resultado": "-1R",
      "order_id": "d3302a7c-9ed5-4c4b-9811-478c8676b1be",
      "tipo": "M1_SWING_SHORT",
      "fechamento": "11/06/2026 16:34"
    },
    {
      "id": 201,
      "symbol": "TRXUSDT",
      "direcao": "up",
      "entrada": 0.313729,
      "stop": 0.31308069,
      "alvo": 0.31567392999999994,
      "risco": 0.0006483099999999853,
      "rr": 3.0,
      "data": "11/06/2026 16:31",
      "status": "loss",
      "resultado": "-1R",
      "order_id": "565ebdf6-95f6-42a7-823f-c39d2ab4c6c1",
      "tipo": "EW_TRI_E_LONG",
      "fechamento": "11/06/2026 17:02"
    },
    {
      "id": 201,
      "symbol": "ETHUSDT",
      "direcao": "down",
      "entrada": 1687.45,
      "stop": 1689.2716629999998,
      "alvo": 1681.985011000001,
      "risco": 1.8216629999997167,
      "rr": 3.0,
      "data": "11/06/2026 16:35",
      "status": "win",
      "resultado": "+3.0R",
      "order_id": null,
      "tipo": "EW_W2_SHORT",
      "fechamento": "11/06/2026 16:58"
    },
    {
      "id": 201,
      "symbol": "TRXUSDT",
      "direcao": "up",
      "entrada": 0.31363,
      "stop": 0.31308069,
      "alvo": 0.3152779300000001,
      "risco": 0.0005493100000000251,
      "rr": 3.0,
      "data": "11/06/2026 16:40",
      "status": "loss",
      "resultado": "-1R",
      "order_id": null,
      "tipo": "EW_TRI_E_LONG",
      "fechamento": "11/06/2026 17:02"
    },
    {
      "id": 201,
      "symbol": "ETHUSDT",
      "direcao": "up",
      "entrada": 1682.54,
      "stop": 1678.0725519999999,
      "alvo": 1695.9423440000003,
      "risco": 4.467448000000104,
      "rr": 3.0,
      "data": "11/06/2026 17:01",
      "status": "loss",
      "resultado": "-1R",
      "order_id": "abd30fe2-323c-40a4-8b28-53b4dcff5787",
      "tipo": "M1_SWING_LONG",
      "fechamento": "11/06/2026 17:27"
    },
    {
      "id": 201,
      "symbol": "TRXUSDT",
      "direcao": "up",
      "entrada": 0.313139,
      "stop": 0.31308069,
      "alvo": 0.31331393,
      "risco": 5.831000000000586e-05,
      "rr": 3.0,
      "data": "11/06/2026 17:01",
      "status": "loss",
      "resultado": "-1R",
      "order_id": null,
      "tipo": "EW_TRI_E_LONG",
      "fechamento": "11/06/2026 17:02"
    },
    {
      "id": 201,
      "symbol": "ETHUSDT",
      "direcao": "down",
      "entrada": 1672.8,
      "stop": 1679.186908,
      "alvo": 1653.639276,
      "risco": 6.3869079999999485,
      "rr": 3.0,
      "data": "11/06/2026 17:34",
      "status": "loss",
      "resultado": "-1R",
      "order_id": "86978f22-0f5e-4917-93a3-ed2ac599982a",
      "tipo": "M1_SWING_SHORT",
      "fechamento": "11/06/2026 18:14"
    },
    {
      "id": 201,
      "symbol": "ETHUSDT",
      "direcao": "up",
      "entrada": 1671.19,
      "stop": 1668.368378,
      "alvo": 1679.6548660000005,
      "risco": 2.8216220000001613,
      "rr": 3.0,
      "data": "11/06/2026 17:37",
      "status": "win",
      "resultado": "+3.0R",
      "order_id": null,
      "tipo": "M1_SWING_LONG",
      "fechamento": "11/06/2026 18:14"
    },
    {
      "id": 201,
      "symbol": "ETHUSDT",
      "direcao": "up",
      "entrada": 1670.62,
      "stop": 1668.368378,
      "alvo": 1677.3748659999999,
      "risco": 2.2516219999999976,
      "rr": 3.0,
      "data": "11/06/2026 17:52",
      "status": "win",
      "resultado": "+3.0R",
      "order_id": "1881e9a8-30de-4fc2-b20f-104c47c8cd19",
      "tipo": "M1_SWING_LONG",
      "fechamento": "11/06/2026 18:14"
    },
    {
      "id": 201,
      "symbol": "ETHUSDT",
      "direcao": "down",
      "entrada": 1672.31,
      "stop": 1679.186908,
      "alvo": 1651.679276,
      "risco": 6.876907999999958,
      "rr": 3.0,
      "data": "11/06/2026 17:57",
      "status": "loss",
      "resultado": "-1R",
      "order_id": "54a6d4bb-da35-41a4-9cf1-f0a02a13d228",
      "tipo": "M1_SWING_SHORT",
      "fechamento": "11/06/2026 18:14"
    },
    {
      "id": 201,
      "symbol": "ETHUSDT",
      "direcao": "up",
      "entrada": 1681.54,
      "stop": 1679.5616579999999,
      "alvo": 1687.4750260000003,
      "risco": 1.9783420000001115,
      "rr": 3.0,
      "data": "11/06/2026 18:16",
      "status": "loss",
      "resultado": "-1R",
      "order_id": "f6572738-20ab-4599-b689-aadd7f2a78d4",
      "tipo": "M1_SWING_LONG",
      "fechamento": "11/06/2026 18:26"
    },
    {
      "id": 201,
      "symbol": "ETHUSDT",
      "direcao": "up",
      "entrada": 1680.42,
      "stop": 1677.962618,
      "alvo": 1687.7921460000002,
      "risco": 2.4573820000000524,
      "rr": 3.0,
      "data": "11/06/2026 18:22",
      "status": "loss",
      "resultado": "-1R",
      "order_id": "46e4aee3-9aa6-406d-b86e-394692a990d9",
      "tipo": "M1_SWING_LONG",
      "fechamento": "11/06/2026 18:56"
    },
    {
      "id": 201,
      "symbol": "ETHUSDT",
      "direcao": "down",
      "entrada": 1679.71,
      "stop": 1682.548924,
      "alvo": 1671.1932280000003,
      "risco": 2.8389239999999063,
      "rr": 3.0,
      "data": "11/06/2026 18:41",
      "status": "win",
      "resultado": "+3.0R",
      "order_id": "9d4db421-9f55-4299-8f3e-f79a532e2857",
      "tipo": "M1_SWING_SHORT",
      "fechamento": "11/06/2026 20:30"
    },
    {
      "id": 201,
      "symbol": "ETHUSDT",
      "direcao": "up",
      "entrada": 1677.23,
      "stop": 1671.3865660000001,
      "alvo": 1694.7603019999997,
      "risco": 5.843433999999888,
      "rr": 3.0,
      "data": "11/06/2026 19:00",
      "status": "loss",
      "resultado": "-1R",
      "order_id": "9f905529-3dbf-4abd-bd0f-34e9b2f44dbb",
      "tipo": "M1_SWING_LONG",
      "fechamento": "11/06/2026 20:30"
    },
    {
      "id": 201,
      "symbol": "ETHUSDT",
      "direcao": "up",
      "entrada": 1677.23,
      "stop": 1671.3865660000001,
      "alvo": 1694.7603019999997,
      "risco": 5.843433999999888,
      "rr": 3.0,
      "data": "11/06/2026 19:01",
      "status": "loss",
      "resultado": "-1R",
      "order_id": "b7782ee7-ec2e-4c35-b2d1-24e02a296116",
      "tipo": "M1_SWING_LONG",
      "fechamento": "11/06/2026 20:30"
    },
    {
      "id": 201,
      "symbol": "ETHUSDT",
      "direcao": "down",
      "entrada": 1681.2,
      "stop": 1682.24472,
      "alvo": 1678.0658400000004,
      "risco": 1.0447199999998702,
      "rr": 3.0,
      "data": "11/06/2026 19:05",
      "status": "loss",
      "resultado": "-1R",
      "order_id": "ee9caad1-6d04-48bb-acee-1120d3fcc348",
      "tipo": "EW_TRI_E_SHORT",
      "fechamento": "11/06/2026 19:18"
    },
    {
      "id": 201,
      "symbol": "ETHUSDT",
      "direcao": "up",
      "entrada": 1680.5,
      "stop": 1677.7227619999999,
      "alvo": 1688.8317140000004,
      "risco": 2.777238000000125,
      "rr": 3.0,
      "data": "11/06/2026 19:14",
      "status": "loss",
      "resultado": "-1R",
      "order_id": "69a0b3fd-3e56-4beb-a14c-692fec94fbc6",
      "tipo": "M1_SWING_LONG",
      "fechamento": "11/06/2026 19:26"
    },
    {
      "id": 201,
      "symbol": "ETHUSDT",
      "direcao": "down",
      "entrada": 1680.84,
      "stop": 1682.24472,
      "alvo": 1676.62584,
      "risco": 1.4047199999999975,
      "rr": 3.0,
      "data": "11/06/2026 19:16",
      "status": "loss",
      "resultado": "-1R",
      "order_id": "7aa8c75a-397d-4ab9-85a0-14578734fbd9",
      "tipo": "EW_TRI_E_SHORT",
      "fechamento": "11/06/2026 19:18"
    },
    {
      "id": 201,
      "symbol": "TONUSDT",
      "direcao": "up",
      "entrada": 1.7107,
      "stop": 1.70630475,
      "alvo": 1.7238857500000007,
      "risco": 0.004395250000000184,
      "rr": 3.0,
      "data": "11/06/2026 19:32",
      "status": "loss",
      "resultado": "-1R",
      "order_id": null,
      "tipo": "EW_W2_LONG",
      "fechamento": "11/06/2026 19:38"
    },
    {
      "id": 201,
      "symbol": "BNBUSDT",
      "direcao": "up",
      "entrada": 606.13,
      "stop": 603.47727,
      "alvo": 614.08819,
      "risco": 2.6527300000000196,
      "rr": 3.0,
      "data": "12/06/2026 00:00",
      "status": "loss",
      "resultado": "-1R",
      "order_id": "bf3480d6-17c7-473b-8ccf-cfe05b50c243",
      "tipo": "M1_W_LONG",
      "fechamento": "12/06/2026 00:24"
    },
    {
      "id": 201,
      "symbol": "NEARUSDT",
      "direcao": "down",
      "entrada": 2.0758,
      "stop": 2.1040616799999996,
      "alvo": 2.0456,
      "risco": 0.02826167999999951,
      "rr": 1.1,
      "data": "12/06/2026 11:07",
      "status": "loss",
      "resultado": "-1R",
      "order_id": null,
      "tipo": "M1_SWING_SHORT",
      "fechamento": "12/06/2026 12:06"
    },
    {
      "id": 201,
      "symbol": "BTCUSDT",
      "direcao": "up",
      "entrada": 63415.8,
      "stop": 63050.73357,
      "alvo": 63781.299999999996,
      "risco": 365.0664300000062,
      "rr": 1.0,
      "data": "12/06/2026 11:10",
      "status": "win",
      "resultado": "+1.0R",
      "order_id": null,
      "tipo": "M1_W_LONG",
      "fechamento": "12/06/2026 11:53"
    },
    {
      "id": 201,
      "symbol": "BTCUSDT",
      "direcao": "down",
      "entrada": 63396.7,
      "stop": 63558.35973,
      "alvo": 63213.299999999996,
      "risco": 161.6597299999994,
      "rr": 1.1,
      "data": "12/06/2026 11:12",
      "status": "loss",
      "resultado": "-1R",
      "order_id": null,
      "tipo": "M1_M_SHORT",
      "fechamento": "12/06/2026 11:28"
    },
    {
      "id": 201,
      "symbol": "ETHUSDT",
      "direcao": "up",
      "entrada": 1664.02,
      "stop": 1659.223868,
      "alvo": 1668.88,
      "risco": 4.796131999999943,
      "rr": 1.0,
      "data": "12/06/2026 11:13",
      "status": "win",
      "resultado": "+1.0R",
      "order_id": "7762e5c5-c098-4cdb-9cb4-91c938e2e0b6",
      "tipo": "M1_SWING_LONG",
      "fechamento": "12/06/2026 11:29"
    },
    {
      "id": 201,
      "symbol": "SOLUSDT",
      "direcao": "up",
      "entrada": 66.89,
      "stop": 66.483429,
      "alvo": 67.57,
      "risco": 0.40657099999999957,
      "rr": 1.7,
      "data": "12/06/2026 11:13",
      "status": "win",
      "resultado": "+1.7R",
      "order_id": "d2570e58-546d-43a6-bc1d-4b19796c10d3",
      "tipo": "M1_W_LONG",
      "fechamento": "12/06/2026 11:53"
    },
    {
      "id": 201,
      "symbol": "BTCUSDT",
      "direcao": "up",
      "entrada": 63396.7,
      "stop": 63050.73357,
      "alvo": 63781.299999999996,
      "risco": 345.9664300000004,
      "rr": 1.1,
      "data": "12/06/2026 11:13",
      "status": "win",
      "resultado": "+1.1R",
      "order_id": null,
      "tipo": "M1_W_LONG",
      "fechamento": "12/06/2026 11:53"
    },
    {
      "id": 201,
      "symbol": "SOLUSDT",
      "direcao": "up",
      "entrada": 66.91,
      "stop": 66.483429,
      "alvo": 67.57,
      "risco": 0.4265709999999956,
      "rr": 1.5,
      "data": "12/06/2026 11:15",
      "status": "win",
      "resultado": "+1.5R",
      "order_id": "6426b24f-3866-4d18-b106-1f0860cd1a84",
      "tipo": "M1_W_LONG",
      "fechamento": "12/06/2026 11:53"
    },
    {
      "id": 201,
      "symbol": "NEARUSDT",
      "direcao": "up",
      "entrada": 2.0688,
      "stop": 2.04416808,
      "alvo": 2.0996,
      "risco": 0.02463192000000003,
      "rr": 1.3,
      "data": "12/06/2026 11:16",
      "status": "win",
      "resultado": "+1.3R",
      "order_id": null,
      "tipo": "M1_W_LONG",
      "fechamento": "12/06/2026 12:06"
    },
    {
      "id": 201,
      "symbol": "BTCUSDT",
      "direcao": "up",
      "entrada": 63482.7,
      "stop": 63319.24548,
      "alvo": 63664.200000000004,
      "risco": 163.45451999999932,
      "rr": 1.1,
      "data": "12/06/2026 11:16",
      "status": "win",
      "resultado": "+1.1R",
      "order_id": null,
      "tipo": "M1_W_LONG",
      "fechamento": "12/06/2026 11:35"
    },
    {
      "id": 201,
      "symbol": "TONUSDT",
      "direcao": "up",
      "entrada": 1.7469,
      "stop": 1.71899586,
      "alvo": 1.7806,
      "risco": 0.027904139999999966,
      "rr": 1.2,
      "data": "12/06/2026 11:18",
      "status": "loss",
      "resultado": "-1R",
      "order_id": null,
      "tipo": "M1_W_LONG",
      "fechamento": "12/06/2026 12:59"
    },
    {
      "id": 201,
      "symbol": "SOLUSDT",
      "direcao": "up",
      "entrada": 67.0,
      "stop": 66.483429,
      "alvo": 67.57,
      "risco": 0.516570999999999,
      "rr": 1.1,
      "data": "12/06/2026 11:18",
      "status": "win",
      "resultado": "+1.1R",
      "order_id": "e6d45735-cc0e-449b-a43a-eb9bf475e9a4",
      "tipo": "M1_W_LONG",
      "fechamento": "12/06/2026 11:53"
    },
    {
      "id": 201,
      "symbol": "ETHUSDT",
      "direcao": "up",
      "entrada": 1664.13,
      "stop": 1653.811521,
      "alvo": 1675.45,
      "risco": 10.318479000000025,
      "rr": 1.1,
      "data": "12/06/2026 11:20",
      "status": "win",
      "resultado": "+1.1R",
      "order_id": null,
      "tipo": "M1_W_LONG",
      "fechamento": "12/06/2026 11:53"
    },
    {
      "id": 201,
      "symbol": "SOLUSDT",
      "direcao": "up",
      "entrada": 66.9,
      "stop": 66.483429,
      "alvo": 67.57,
      "risco": 0.4165710000000047,
      "rr": 1.6,
      "data": "12/06/2026 11:20",
      "status": "win",
      "resultado": "+1.6R",
      "order_id": "3c9e6bce-42a6-45bd-a9e6-7895a73e6957",
      "tipo": "M1_W_LONG",
      "fechamento": "12/06/2026 11:53"
    },
    {
      "id": 201,
      "symbol": "TONUSDT",
      "direcao": "up",
      "entrada": 1.7429,
      "stop": 1.71899586,
      "alvo": 1.7806,
      "risco": 0.023904139999999963,
      "rr": 1.6,
      "data": "12/06/2026 11:20",
      "status": "loss",
      "resultado": "-1R",
      "order_id": null,
      "tipo": "M1_W_LONG",
      "fechamento": "12/06/2026 12:59"
    },
    {
      "id": 201,
      "symbol": "ETHUSDT",
      "direcao": "up",
      "entrada": 1664.13,
      "stop": 1653.811521,
      "alvo": 1675.45,
      "risco": 10.318479000000025,
      "rr": 1.1,
      "data": "12/06/2026 11:22",
      "status": "win",
      "resultado": "+1.1R",
      "order_id": null,
      "tipo": "M1_W_LONG",
      "fechamento": "12/06/2026 11:53"
    },
    {
      "id": 201,
      "symbol": "BTCUSDT",
      "direcao": "up",
      "entrada": 63367.9,
      "stop": 63050.73357,
      "alvo": 63781.299999999996,
      "risco": 317.16643000000477,
      "rr": 1.3,
      "data": "12/06/2026 11:22",
      "status": "win",
      "resultado": "+1.3R",
      "order_id": null,
      "tipo": "M1_W_LONG",
      "fechamento": "12/06/2026 11:53"
    },
    {
      "id": 201,
      "symbol": "ETHUSDT",
      "direcao": "down",
      "entrada": 1663.37,
      "stop": 1670.1850799999997,
      "alvo": 1654.97,
      "risco": 6.815079999999853,
      "rr": 1.2,
      "data": "12/06/2026 11:24",
      "status": "loss",
      "resultado": "-1R",
      "order_id": null,
      "tipo": "EW_ABC_LEG_C_SHORT",
      "fechamento": "12/06/2026 11:29"
    },
    {
      "id": 201,
      "symbol": "TONUSDT",
      "direcao": "up",
      "entrada": 1.7406,
      "stop": 1.71899586,
      "alvo": 1.7806,
      "risco": 0.021604139999999994,
      "rr": 1.9,
      "data": "12/06/2026 11:24",
      "status": "loss",
      "resultado": "-1R",
      "order_id": null,
      "tipo": "M1_W_LONG",
      "fechamento": "12/06/2026 12:59"
    },
    {
      "id": 201,
      "symbol": "BTCUSDT",
      "direcao": "up",
      "entrada": 63477.4,
      "stop": 63319.24548,
      "alvo": 63664.200000000004,
      "risco": 158.15452000000369,
      "rr": 1.2,
      "data": "12/06/2026 11:25",
      "status": "win",
      "resultado": "+1.2R",
      "order_id": null,
      "tipo": "M1_W_LONG",
      "fechamento": "12/06/2026 11:35"
    },
    {
      "id": 201,
      "symbol": "NEARUSDT",
      "direcao": "up",
      "entrada": 2.0651,
      "stop": 2.04416808,
      "alvo": 2.0996,
      "risco": 0.020931920000000215,
      "rr": 1.6,
      "data": "12/06/2026 11:25",
      "status": "win",
      "resultado": "+1.6R",
      "order_id": null,
      "tipo": "M1_W_LONG",
      "fechamento": "12/06/2026 12:06"
    },
    {
      "id": 201,
      "symbol": "TONUSDT",
      "direcao": "up",
      "entrada": 1.7414,
      "stop": 1.71899586,
      "alvo": 1.7806,
      "risco": 0.022404140000000128,
      "rr": 1.7,
      "data": "12/06/2026 11:26",
      "status": "loss",
      "resultado": "-1R",
      "order_id": null,
      "tipo": "M1_W_LONG",
      "fechamento": "12/06/2026 12:59"
    },
    {
      "id": 201,
      "symbol": "ETHUSDT",
      "direcao": "down",
      "entrada": 1666.46,
      "stop": 1669.881328,
      "alvo": 1663.01,
      "risco": 3.421327999999903,
      "rr": 1.0,
      "data": "12/06/2026 11:26",
      "status": "loss",
      "resultado": "-1R",
      "order_id": null,
      "tipo": "M1_SWING_SHORT",
      "fechamento": "12/06/2026 11:29"
    },
    {
      "id": 201,
      "symbol": "NEARUSDT",
      "direcao": "up",
      "entrada": 2.0699,
      "stop": 2.04416808,
      "alvo": 2.0996,
      "risco": 0.02573192000000013,
      "rr": 1.2,
      "data": "12/06/2026 11:28",
      "status": "win",
      "resultado": "+1.2R",
      "order_id": null,
      "tipo": "M1_W_LONG",
      "fechamento": "12/06/2026 12:06"
    },
    {
      "id": 201,
      "symbol": "TONUSDT",
      "direcao": "up",
      "entrada": 1.744,
      "stop": 1.71899586,
      "alvo": 1.7806,
      "risco": 0.025004140000000064,
      "rr": 1.5,
      "data": "12/06/2026 11:29",
      "status": "loss",
      "resultado": "-1R",
      "order_id": null,
      "tipo": "M1_W_LONG",
      "fechamento": "12/06/2026 12:59"
    },
    {
      "id": 201,
      "symbol": "NEARUSDT",
      "direcao": "up",
      "entrada": 2.0705,
      "stop": 2.04416808,
      "alvo": 2.0996,
      "risco": 0.026331920000000064,
      "rr": 1.1,
      "data": "12/06/2026 11:30",
      "status": "win",
      "resultado": "+1.1R",
      "order_id": null,
      "tipo": "M1_W_LONG",
      "fechamento": "12/06/2026 12:06"
    },
    {
      "id": 201,
      "symbol": "TONUSDT",
      "direcao": "up",
      "entrada": 1.7416,
      "stop": 1.71899586,
      "alvo": 1.7806,
      "risco": 0.022604140000000106,
      "rr": 1.7,
      "data": "12/06/2026 11:31",
      "status": "loss",
      "resultado": "-1R",
      "order_id": null,
      "tipo": "M1_W_LONG",
      "fechamento": "12/06/2026 12:59"
    },
    {
      "id": 201,
      "symbol": "NEARUSDT",
      "direcao": "up",
      "entrada": 2.0652,
      "stop": 2.04416808,
      "alvo": 2.0996,
      "risco": 0.021031919999999982,
      "rr": 1.6,
      "data": "12/06/2026 11:33",
      "status": "win",
      "resultado": "+1.6R",
      "order_id": null,
      "tipo": "M1_W_LONG",
      "fechamento": "12/06/2026 12:06"
    },
    {
      "id": 201,
      "symbol": "NEARUSDT",
      "direcao": "up",
      "entrada": 2.0674,
      "stop": 2.0458668899999997,
      "alvo": 2.1019000000000005,
      "risco": 0.021533110000000466,
      "rr": 1.6,
      "data": "12/06/2026 11:34",
      "status": "win",
      "resultado": "+1.6R",
      "order_id": null,
      "tipo": "M1_W_LONG",
      "fechamento": "12/06/2026 12:06"
    },
    {
      "id": 201,
      "symbol": "NEARUSDT",
      "direcao": "down",
      "entrada": 2.0715,
      "stop": 2.0787541099999998,
      "alvo": 2.0456,
      "risco": 0.007254109999999869,
      "rr": 3.6,
      "data": "12/06/2026 11:35",
      "status": "loss",
      "resultado": "-1R",
      "order_id": null,
      "tipo": "EW_W2_SHORT",
      "fechamento": "12/06/2026 11:53"
    },
    {
      "id": 201,
      "symbol": "NEARUSDT",
      "direcao": "up",
      "entrada": 2.0676,
      "stop": 2.0458668899999997,
      "alvo": 2.1019000000000005,
      "risco": 0.021733110000000444,
      "rr": 1.6,
      "data": "12/06/2026 11:36",
      "status": "win",
      "resultado": "+1.6R",
      "order_id": null,
      "tipo": "M1_W_LONG",
      "fechamento": "12/06/2026 12:06"
    },
    {
      "id": 201,
      "symbol": "NEARUSDT",
      "direcao": "down",
      "entrada": 2.0714,
      "stop": 2.0787541099999998,
      "alvo": 2.0456,
      "risco": 0.007354109999999636,
      "rr": 3.5,
      "data": "12/06/2026 11:37",
      "status": "loss",
      "resultado": "-1R",
      "order_id": null,
      "tipo": "EW_W2_SHORT",
      "fechamento": "12/06/2026 11:53"
    },
    {
      "id": 201,
      "symbol": "NEARUSDT",
      "direcao": "up",
      "entrada": 2.0734,
      "stop": 2.0458668899999997,
      "alvo": 2.1019000000000005,
      "risco": 0.02753311000000025,
      "rr": 1.0,
      "data": "12/06/2026 11:39",
      "status": "win",
      "resultado": "+1.0R",
      "order_id": null,
      "tipo": "M1_W_LONG",
      "fechamento": "12/06/2026 12:06"
    },
    {
      "id": 201,
      "symbol": "NEARUSDT",
      "direcao": "up",
      "entrada": 2.0738,
      "stop": 2.0458668899999997,
      "alvo": 2.1019000000000005,
      "risco": 0.027933110000000205,
      "rr": 1.0,
      "data": "12/06/2026 11:39",
      "status": "win",
      "resultado": "+1.0R",
      "order_id": null,
      "tipo": "M1_W_LONG",
      "fechamento": "12/06/2026 12:06"
    },
    {
      "id": 201,
      "symbol": "NEARUSDT",
      "direcao": "down",
      "entrada": 2.0738,
      "stop": 2.0787541099999998,
      "alvo": 2.0456,
      "risco": 0.0049541099999999005,
      "rr": 5.7,
      "data": "12/06/2026 11:39",
      "status": "loss",
      "resultado": "-1R",
      "order_id": null,
      "tipo": "EW_W2_SHORT",
      "fechamento": "12/06/2026 11:53"
    },
    {
      "id": 201,
      "symbol": "BTCUSDT",
      "direcao": "up",
      "entrada": 63643.7,
      "stop": 63297.96039,
      "alvo": 64037.7,
      "risco": 345.7396099999969,
      "rr": 1.1,
      "data": "12/06/2026 11:41",
      "status": "win",
      "resultado": "+1.1R",
      "order_id": null,
      "tipo": "M1_W_LONG",
      "fechamento": "12/06/2026 12:00"
    },
    {
      "id": 201,
      "symbol": "BTCUSDT",
      "direcao": "down",
      "entrada": 63643.7,
      "stop": 63809.235219999995,
      "alvo": 63411.4,
      "risco": 165.53521999999793,
      "rr": 1.4,
      "data": "12/06/2026 11:41",
      "status": "loss",
      "resultado": "-1R",
      "order_id": null,
      "tipo": "M1_M_SHORT",
      "fechamento": "12/06/2026 11:53"
    },
    {
      "id": 201,
      "symbol": "DOGEUSDT",
      "direcao": "down",
      "entrada": 0.0916161,
      "stop": 0.09245157082999998,
      "alvo": 0.0905905,
      "risco": 0.0008354708299999763,
      "rr": 1.2,
      "data": "12/06/2026 11:42",
      "status": "win",
      "resultado": "+1.2R",
      "order_id": null,
      "tipo": "M1_PULLBACK_SHORT",
      "fechamento": "12/06/2026 11:44"
    },
    {
      "id": 201,
      "symbol": "ETHUSDT",
      "direcao": "down",
      "entrada": 1671.53,
      "stop": 1676.592794,
      "alvo": 1664.8199999999997,
      "risco": 5.06279399999994,
      "rr": 1.3,
      "data": "12/06/2026 11:42",
      "status": "loss",
      "resultado": "-1R",
      "order_id": null,
      "tipo": "M1_M_SHORT",
      "fechamento": "12/06/2026 11:53"
    },
    {
      "id": 201,
      "symbol": "NEARUSDT",
      "direcao": "down",
      "entrada": 2.0685,
      "stop": 2.0787541099999998,
      "alvo": 2.0456,
      "risco": 0.010254109999999983,
      "rr": 2.2,
      "data": "12/06/2026 11:42",
      "status": "loss",
      "resultado": "-1R",
      "order_id": null,
      "tipo": "EW_W2_SHORT",
      "fechamento": "12/06/2026 11:54"
    },
    {
      "id": 201,
      "symbol": "BTCUSDT",
      "direcao": "down",
      "entrada": 63612.6,
      "stop": 63558.35973,
      "alvo": 62918.5,
      "risco": 54.240270000002056,
      "rr": 12.8,
      "data": "12/06/2026 11:42",
      "status": "loss",
      "resultado": "-1R",
      "order_id": null,
      "tipo": "EW_W2_SHORT",
      "fechamento": "12/06/2026 11:42"
    },
    {
      "id": 201,
      "symbol": "NEARUSDT",
      "direcao": "down",
      "entrada": 2.0545,
      "stop": 2.0760522200000002,
      "alvo": 2.0199999999999996,
      "risco": 0.021552220000000233,
      "rr": 1.6,
      "data": "12/06/2026 11:43",
      "status": "loss",
      "resultado": "-1R",
      "order_id": null,
      "tipo": "M1_M_SHORT",
      "fechamento": "12/06/2026 11:54"
    },
    {
      "id": 201,
      "symbol": "BTCUSDT",
      "direcao": "up",
      "entrada": 63521.4,
      "stop": 63325.58184,
      "alvo": 63764.6,
      "risco": 195.81816000000254,
      "rr": 1.2,
      "data": "12/06/2026 11:44",
      "status": "win",
      "resultado": "+1.2R",
      "order_id": null,
      "tipo": "M1_SWING_LONG",
      "fechamento": "12/06/2026 11:54"
    },
    {
      "id": 201,
      "symbol": "ETHUSDT",
      "direcao": "up",
      "entrada": 1669.65,
      "stop": 1661.845893,
      "alvo": 1679.99,
      "risco": 7.804107000000158,
      "rr": 1.3,
      "data": "12/06/2026 11:45",
      "status": "win",
      "resultado": "+1.3R",
      "order_id": null,
      "tipo": "M1_W_LONG",
      "fechamento": "12/06/2026 11:54"
    },
    {
      "id": 201,
      "symbol": "BTCUSDT",
      "direcao": "down",
      "entrada": 63552.4,
      "stop": 63558.35973,
      "alvo": 62918.5,
      "risco": 5.959729999995034,
      "rr": 106.4,
      "data": "12/06/2026 11:45",
      "status": "loss",
      "resultado": "-1R",
      "order_id": null,
      "tipo": "EW_W2_SHORT",
      "fechamento": "12/06/2026 11:52"
    },
    {
      "id": 201,
      "symbol": "BTCUSDT",
      "direcao": "up",
      "entrada": 63524.2,
      "stop": 63325.58184,
      "alvo": 63764.6,
      "risco": 198.61815999999817,
      "rr": 1.2,
      "data": "12/06/2026 11:46",
      "status": "win",
      "resultado": "+1.2R",
      "order_id": "44b3f653-0201-4c1e-8585-68c9a399d5f3",
      "tipo": "M1_SWING_LONG",
      "fechamento": "12/06/2026 11:54"
    },
    {
      "id": 201,
      "symbol": "ETHUSDT",
      "direcao": "up",
      "entrada": 1670.12,
      "stop": 1661.845893,
      "alvo": 1679.99,
      "risco": 8.274106999999958,
      "rr": 1.2,
      "data": "12/06/2026 11:47",
      "status": "win",
      "resultado": "+1.2R",
      "order_id": null,
      "tipo": "M1_W_LONG",
      "fechamento": "12/06/2026 11:54"
    },
    {
      "id": 201,
      "symbol": "BTCUSDT",
      "direcao": "up",
      "entrada": 63506.8,
      "stop": 63325.58184,
      "alvo": 63690.0,
      "risco": 181.218160000004,
      "rr": 1.0,
      "data": "12/06/2026 11:47",
      "status": "win",
      "resultado": "+1.0R",
      "order_id": null,
      "tipo": "M1_SWING_LONG",
      "fechamento": "12/06/2026 11:54"
    },
    {
      "id": 201,
      "symbol": "BTCUSDT",
      "direcao": "down",
      "entrada": 63506.8,
      "stop": 63558.35973,
      "alvo": 62918.5,
      "risco": 51.55972999999358,
      "rr": 11.4,
      "data": "12/06/2026 11:48",
      "status": "loss",
      "resultado": "-1R",
      "order_id": "d68b6c13-6d09-42fc-9269-9b0b55fa4bc9",
      "tipo": "EW_W2_SHORT",
      "fechamento": "12/06/2026 11:52"
    },
    {
      "id": 201,
      "symbol": "BTCUSDT",
      "direcao": "up",
      "entrada": 63503.9,
      "stop": 63333.9768,
      "alvo": 63690.0,
      "risco": 169.92320000000473,
      "rr": 1.1,
      "data": "12/06/2026 11:49",
      "status": "win",
      "resultado": "+1.1R",
      "order_id": "67e2714c-3e0c-48a5-876c-7e8c83500fdc",
      "tipo": "M1_SWING_LONG",
      "fechamento": "12/06/2026 11:54"
    },
    {
      "id": 201,
      "symbol": "ETHUSDT",
      "direcao": "up",
      "entrada": 1668.25,
      "stop": 1663.0215879999998,
      "alvo": 1675.42,
      "risco": 5.228412000000162,
      "rr": 1.4,
      "data": "12/06/2026 11:49",
      "status": "win",
      "resultado": "+1.4R",
      "order_id": null,
      "tipo": "M1_SWING_LONG",
      "fechamento": "12/06/2026 11:54"
    },
    {
      "id": 201,
      "symbol": "DOGEUSDT",
      "direcao": "up",
      "entrada": 0.089573,
      "stop": 0.08691102208,
      "alvo": 0.0923869,
      "risco": 0.0026619779200000027,
      "rr": 1.1,
      "data": "12/06/2026 11:50",
      "status": "aberto",
      "resultado": null,
      "order_id": null,
      "tipo": "M1_SWING_LONG"
    },
    {
      "id": 201,
      "symbol": "LINKUSDT",
      "direcao": "up",
      "entrada": 7.89146,
      "stop": 7.836740439,
      "alvo": 7.99243,
      "risco": 0.05471956100000064,
      "rr": 1.8,
      "data": "12/06/2026 11:50",
      "status": "win",
      "resultado": "+1.8R",
      "order_id": null,
      "tipo": "M1_W_LONG",
      "fechamento": "12/06/2026 12:14"
    },
    {
      "id": 201,
      "symbol": "ETHUSDT",
      "direcao": "up",
      "entrada": 1669.38,
      "stop": 1661.845893,
      "alvo": 1679.99,
      "risco": 7.534107000000176,
      "rr": 1.4,
      "data": "12/06/2026 11:50",
      "status": "win",
      "resultado": "+1.4R",
      "order_id": null,
      "tipo": "M1_W_LONG",
      "fechamento": "12/06/2026 11:54"
    },
    {
      "id": 201,
      "symbol": "ETHUSDT",
      "direcao": "down",
      "entrada": 1669.38,
      "stop": 1676.592794,
      "alvo": 1662.12,
      "risco": 7.212793999999803,
      "rr": 1.0,
      "data": "12/06/2026 11:50",
      "status": "loss",
      "resultado": "-1R",
      "order_id": null,
      "tipo": "M1_M_SHORT",
      "fechamento": "12/06/2026 11:54"
    },
    {
      "id": 201,
      "symbol": "NEARUSDT",
      "direcao": "up",
      "entrada": 2.0605,
      "stop": 2.04566216,
      "alvo": 2.0759,
      "risco": 0.014837840000000213,
      "rr": 1.0,
      "data": "12/06/2026 11:50",
      "status": "win",
      "resultado": "+1.0R",
      "order_id": null,
      "tipo": "EW_TRI_LEG_D_LONG",
      "fechamento": "12/06/2026 11:54"
    },
    {
      "id": 201,
      "symbol": "BTCUSDT",
      "direcao": "up",
      "entrada": 63547.8,
      "stop": 63333.9768,
      "alvo": 63764.6,
      "risco": 213.82320000000618,
      "rr": 1.0,
      "data": "12/06/2026 11:51",
      "status": "win",
      "resultado": "+1.0R",
      "order_id": null,
      "tipo": "M1_SWING_LONG",
      "fechamento": "12/06/2026 11:54"
    },
    {
      "id": 201,
      "symbol": "DOGEUSDT",
      "direcao": "up",
      "entrada": 0.0897467,
      "stop": 0.08719085408,
      "alvo": 0.0923869,
      "risco": 0.002555845919999994,
      "rr": 1.0,
      "data": "12/06/2026 11:52",
      "status": "aberto",
      "resultado": null,
      "order_id": null,
      "tipo": "M1_SWING_LONG"
    },
    {
      "id": 201,
      "symbol": "BTCUSDT",
      "direcao": "up",
      "entrada": 63638.0,
      "stop": 63297.96039,
      "alvo": 64037.7,
      "risco": 340.0396099999998,
      "rr": 1.2,
      "data": "12/06/2026 11:52",
      "status": "win",
      "resultado": "+1.2R",
      "order_id": null,
      "tipo": "M1_W_LONG",
      "fechamento": "12/06/2026 12:00"
    },
    {
      "id": 201,
      "symbol": "BTCUSDT",
      "direcao": "down",
      "entrada": 63638.0,
      "stop": 63809.235219999995,
      "alvo": 63411.4,
      "risco": 171.23521999999502,
      "rr": 1.3,
      "data": "12/06/2026 11:52",
      "status": "loss",
      "resultado": "-1R",
      "order_id": "5fa229cf-e9a1-4444-826a-7d819e12c9f2",
      "tipo": "M1_M_SHORT",
      "fechamento": "12/06/2026 11:54"
    },
    {
      "id": 201,
      "symbol": "BNBUSDT",
      "direcao": "up",
      "entrada": 607.99,
      "stop": 605.016192,
      "alvo": 611.6199999999999,
      "risco": 2.9738079999999627,
      "rr": 1.2,
      "data": "12/06/2026 11:53",
      "status": "win",
      "resultado": "+1.2R",
      "order_id": "a966f4c7-53a7-4425-9f4a-d5be192fa921",
      "tipo": "M1_W_LONG",
      "fechamento": "12/06/2026 12:14"
    },
    {
      "id": 201,
      "symbol": "DOGEUSDT",
      "direcao": "down",
      "entrada": 0.0900474,
      "stop": 0.09245157082999998,
      "alvo": 0.08686250000000001,
      "risco": 0.0024041708299999826,
      "rr": 1.3,
      "data": "12/06/2026 11:56",
      "status": "aberto",
      "resultado": null,
      "order_id": "b684dd7c-bde7-471e-bb3d-ac518aecf604",
      "tipo": "M1_M_SHORT"
    },
    {
      "id": 201,
      "symbol": "NEARUSDT",
      "direcao": "down",
      "entrada": 2.0793,
      "stop": 2.0787541099999998,
      "alvo": 2.0456,
      "risco": 0.0005458900000001599,
      "rr": 61.7,
      "data": "12/06/2026 11:56",
      "status": "loss",
      "resultado": "-1R",
      "order_id": null,
      "tipo": "EW_W2_SHORT",
      "fechamento": "12/06/2026 11:56"
    },
    {
      "id": 201,
      "symbol": "DOGEUSDT",
      "direcao": "down",
      "entrada": 0.0903845,
      "stop": 0.09245157082999998,
      "alvo": 0.08686250000000001,
      "risco": 0.0020670708299999757,
      "rr": 1.7,
      "data": "12/06/2026 11:58",
      "status": "aberto",
      "resultado": null,
      "order_id": "60ff92c8-3daa-4d9c-8980-6061ba8d7b4f",
      "tipo": "M1_M_SHORT"
    },
    {
      "id": 201,
      "symbol": "NEARUSDT",
      "direcao": "down",
      "entrada": 2.082,
      "stop": 2.0787541099999998,
      "alvo": 2.0456,
      "risco": 0.0032458900000000845,
      "rr": 11.2,
      "data": "12/06/2026 11:59",
      "status": "loss",
      "resultado": "-1R",
      "order_id": null,
      "tipo": "EW_W2_SHORT",
      "fechamento": "12/06/2026 11:59"
    },
    {
      "id": 201,
      "symbol": "DOGEUSDT",
      "direcao": "down",
      "entrada": 0.0905711,
      "stop": 0.09245157082999998,
      "alvo": 0.08686250000000001,
      "risco": 0.0018804708299999806,
      "rr": 2.0,
      "data": "12/06/2026 12:01",
      "status": "aberto",
      "resultado": null,
      "order_id": "75179957-061a-4e83-9028-d363e3cd1f79",
      "tipo": "M1_M_SHORT"
    },
    {
      "id": 201,
      "symbol": "NEARUSDT",
      "direcao": "up",
      "entrada": 2.0904,
      "stop": 2.0535615000000003,
      "alvo": 2.1278,
      "risco": 0.03683849999999955,
      "rr": 1.0,
      "data": "12/06/2026 12:01",
      "status": "loss",
      "resultado": "-1R",
      "order_id": null,
      "tipo": "M1_W_LONG",
      "fechamento": "12/06/2026 12:49"
    },
    {
      "id": 201,
      "symbol": "DOGEUSDT",
      "direcao": "down",
      "entrada": 0.089945,
      "stop": 0.09245157082999998,
      "alvo": 0.08686250000000001,
      "risco": 0.002506570829999985,
      "rr": 1.2,
      "data": "12/06/2026 12:03",
      "status": "aberto",
      "resultado": null,
      "order_id": "230e06a4-f8fd-4065-a88c-ac231cd88d11",
      "tipo": "M1_M_SHORT"
    },
    {
      "id": 201,
      "symbol": "NEARUSDT",
      "direcao": "up",
      "entrada": 2.0835,
      "stop": 2.0535615000000003,
      "alvo": 2.1278,
      "risco": 0.029938499999999646,
      "rr": 1.5,
      "data": "12/06/2026 12:03",
      "status": "loss",
      "resultado": "-1R",
      "order_id": null,
      "tipo": "M1_W_LONG",
      "fechamento": "12/06/2026 12:49"
    },
    {
      "id": 201,
      "symbol": "NEARUSDT",
      "direcao": "down",
      "entrada": 2.0854,
      "stop": 2.0787541099999998,
      "alvo": 2.0456,
      "risco": 0.006645890000000154,
      "rr": 6.0,
      "data": "12/06/2026 12:04",
      "status": "loss",
      "resultado": "-1R",
      "order_id": null,
      "tipo": "EW_W2_SHORT",
      "fechamento": "12/06/2026 12:04"
    },
    {
      "id": 201,
      "symbol": "DOGEUSDT",
      "direcao": "down",
      "entrada": 0.0900359,
      "stop": 0.09245157082999998,
      "alvo": 0.08686250000000001,
      "risco": 0.00241567082999998,
      "rr": 1.3,
      "data": "12/06/2026 12:06",
      "status": "aberto",
      "resultado": null,
      "order_id": null,
      "tipo": "M1_M_SHORT"
    },
    {
      "id": 201,
      "symbol": "LTCUSDT",
      "direcao": "up",
      "entrada": 43.39712,
      "stop": 43.108862658,
      "alvo": 43.76222,
      "risco": 0.2882573420000014,
      "rr": 1.3,
      "data": "12/06/2026 12:07",
      "status": "loss",
      "resultado": "-1R",
      "order_id": null,
      "tipo": "M1_W_LONG",
      "fechamento": "12/06/2026 12:57"
    },
    {
      "id": 201,
      "symbol": "DOGEUSDT",
      "direcao": "down",
      "entrada": 0.0900254,
      "stop": 0.09245157082999998,
      "alvo": 0.08686250000000001,
      "risco": 0.002426170829999977,
      "rr": 1.3,
      "data": "12/06/2026 12:09",
      "status": "aberto",
      "resultado": null,
      "order_id": null,
      "tipo": "M1_M_SHORT"
    },
    {
      "id": 201,
      "symbol": "ETHUSDT",
      "direcao": "up",
      "entrada": 1684.16,
      "stop": 1667.0822249999999,
      "alvo": 1701.81,
      "risco": 17.0777750000002,
      "rr": 1.0,
      "data": "12/06/2026 12:09",
      "status": "loss",
      "resultado": "-1R",
      "order_id": null,
      "tipo": "M1_W_LONG",
      "fechamento": "12/06/2026 12:49"
    },
    {
      "id": 201,
      "symbol": "ETHUSDT",
      "direcao": "up",
      "entrada": 1683.28,
      "stop": 1680.3311959999999,
      "alvo": 1686.66,
      "risco": 2.9488040000001092,
      "rr": 1.1,
      "data": "12/06/2026 12:10",
      "status": "win",
      "resultado": "+1.1R",
      "order_id": null,
      "tipo": "M1_SWING_LONG",
      "fechamento": "12/06/2026 12:12"
    },
    {
      "id": 201,
      "symbol": "ETHUSDT",
      "direcao": "down",
      "entrada": 1683.28,
      "stop": 1690.9328249999999,
      "alvo": 1672.9299999999998,
      "risco": 7.652824999999893,
      "rr": 1.4,
      "data": "12/06/2026 12:10",
      "status": "win",
      "resultado": "+1.4R",
      "order_id": null,
      "tipo": "M1_M_SHORT",
      "fechamento": "12/06/2026 12:39"
    },
    {
      "id": 201,
      "symbol": "LTCUSDT",
      "direcao": "up",
      "entrada": 43.39712,
      "stop": 43.108862658,
      "alvo": 43.76222,
      "risco": 0.2882573420000014,
      "rr": 1.3,
      "data": "12/06/2026 12:10",
      "status": "loss",
      "resultado": "-1R",
      "order_id": null,
      "tipo": "M1_W_LONG",
      "fechamento": "12/06/2026 12:57"
    },
    {
      "id": 201,
      "symbol": "DOGEUSDT",
      "direcao": "down",
      "entrada": 0.0900477,
      "stop": 0.09245157082999998,
      "alvo": 0.08686250000000001,
      "risco": 0.002403870829999988,
      "rr": 1.3,
      "data": "12/06/2026 12:11",
      "status": "aberto",
      "resultado": null,
      "order_id": null,
      "tipo": "M1_M_SHORT"
    },
    {
      "id": 201,
      "symbol": "ETHUSDT",
      "direcao": "down",
      "entrada": 1687.29,
      "stop": 1690.7638499999998,
      "alvo": 1683.28,
      "risco": 3.4738499999998567,
      "rr": 1.2,
      "data": "12/06/2026 12:16",
      "status": "win",
      "resultado": "+1.2R",
      "order_id": "7ae09026-f874-4828-86ab-793b1b8c1776",
      "tipo": "M1_SWING_SHORT",
      "fechamento": "12/06/2026 12:31"
    },
    {
      "id": 201,
      "symbol": "ETHUSDT",
      "direcao": "down",
      "entrada": 1687.03,
      "stop": 1690.7638499999998,
      "alvo": 1683.28,
      "risco": 3.7338499999998476,
      "rr": 1.0,
      "data": "12/06/2026 12:19",
      "status": "win",
      "resultado": "+1.0R",
      "order_id": null,
      "tipo": "M1_SWING_SHORT",
      "fechamento": "12/06/2026 12:31"
    },
    {
      "id": 201,
      "symbol": "NEARUSDT",
      "direcao": "up",
      "entrada": 2.1146,
      "stop": 2.1059248200000003,
      "alvo": 2.1252,
      "risco": 0.00867517999999956,
      "rr": 1.2,
      "data": "12/06/2026 12:19",
      "status": "loss",
      "resultado": "-1R",
      "order_id": null,
      "tipo": "M1_PULLBACK_LONG",
      "fechamento": "12/06/2026 12:21"
    },
    {
      "id": 201,
      "symbol": "ETHUSDT",
      "direcao": "up",
      "entrada": 1684.86,
      "stop": 1680.3311959999999,
      "alvo": 1690.78,
      "risco": 4.5288040000000365,
      "rr": 1.3,
      "data": "12/06/2026 12:21",
      "status": "loss",
      "resultado": "-1R",
      "order_id": "f13541f3-70a2-42a2-af35-8d08c2394552",
      "tipo": "M1_SWING_LONG",
      "fechamento": "12/06/2026 12:32"
    },
    {
      "id": 201,
      "symbol": "ETHUSDT",
      "direcao": "down",
      "entrada": 1684.86,
      "stop": 1691.963546,
      "alvo": 1675.78,
      "risco": 7.103546000000051,
      "rr": 1.3,
      "data": "12/06/2026 12:21",
      "status": "win",
      "resultado": "+1.3R",
      "order_id": "7f4396bb-05f4-4414-9974-1e5f7606f2f1",
      "tipo": "M1_M_SHORT",
      "fechamento": "12/06/2026 12:35"
    },
    {
      "id": 201,
      "symbol": "TONUSDT",
      "direcao": "up",
      "entrada": 1.747,
      "stop": 1.7204671,
      "alvo": 1.7748,
      "risco": 0.02653290000000008,
      "rr": 1.0,
      "data": "12/06/2026 12:21",
      "status": "loss",
      "resultado": "-1R",
      "order_id": null,
      "tipo": "M1_SWING_LONG",
      "fechamento": "12/06/2026 12:59"
    },
    {
      "id": 201,
      "symbol": "TONUSDT",
      "direcao": "down",
      "entrada": 1.747,
      "stop": 1.7760423599999997,
      "alvo": 1.6905999999999999,
      "risco": 0.0290423599999996,
      "rr": 1.9,
      "data": "12/06/2026 12:21",
      "status": "aberto",
      "resultado": null,
      "order_id": null,
      "tipo": "M1_M_SHORT"
    },
    {
      "id": 201,
      "symbol": "SUIUSDT",
      "direcao": "down",
      "entrada": 0.764,
      "stop": 0.77123949,
      "alvo": 0.7505000000000001,
      "risco": 0.007239490000000015,
      "rr": 1.9,
      "data": "12/06/2026 12:22",
      "status": "win",
      "resultado": "+1.9R",
      "order_id": null,
      "tipo": "M1_M_SHORT",
      "fechamento": "12/06/2026 12:56"
    },
    {
      "id": 201,
      "symbol": "ETHUSDT",
      "direcao": "up",
      "entrada": 1684.86,
      "stop": 1680.3311959999999,
      "alvo": 1690.78,
      "risco": 4.5288040000000365,
      "rr": 1.3,
      "data": "12/06/2026 12:23",
      "status": "loss",
      "resultado": "-1R",
      "order_id": "0dc3990d-44a4-40ca-b605-d5970566342c",
      "tipo": "M1_SWING_LONG",
      "fechamento": "12/06/2026 12:32"
    },
    {
      "id": 201,
      "symbol": "ETHUSDT",
      "direcao": "down",
      "entrada": 1684.86,
      "stop": 1691.963546,
      "alvo": 1675.78,
      "risco": 7.103546000000051,
      "rr": 1.3,
      "data": "12/06/2026 12:23",
      "status": "win",
      "resultado": "+1.3R",
      "order_id": "73507e92-9491-44a3-8566-367307ea35be",
      "tipo": "M1_M_SHORT",
      "fechamento": "12/06/2026 12:35"
    },
    {
      "id": 201,
      "symbol": "TONUSDT",
      "direcao": "up",
      "entrada": 1.7475,
      "stop": 1.7204671,
      "alvo": 1.7748,
      "risco": 0.027032900000000026,
      "rr": 1.0,
      "data": "12/06/2026 12:24",
      "status": "loss",
      "resultado": "-1R",
      "order_id": null,
      "tipo": "M1_SWING_LONG",
      "fechamento": "12/06/2026 12:59"
    },
    {
      "id": 201,
      "symbol": "SOLUSDT",
      "direcao": "up",
      "entrada": 68.43,
      "stop": 67.642617,
      "alvo": 69.53,
      "risco": 0.7873830000000055,
      "rr": 1.4,
      "data": "12/06/2026 12:25",
      "status": "loss",
      "resultado": "-1R",
      "order_id": "d70b6edc-e89e-4aba-ae5c-189e3461436a",
      "tipo": "M1_W_LONG",
      "fechamento": "12/06/2026 12:48"
    },
    {
      "id": 201,
      "symbol": "ETHUSDT",
      "direcao": "up",
      "entrada": 1686.26,
      "stop": 1682.270032,
      "alvo": 1690.78,
      "risco": 3.98996800000009,
      "rr": 1.1,
      "data": "12/06/2026 12:25",
      "status": "loss",
      "resultado": "-1R",
      "order_id": "74540765-620e-460e-852a-63b98eb2f3de",
      "tipo": "M1_SWING_LONG",
      "fechamento": "12/06/2026 12:31"
    },
    {
      "id": 201,
      "symbol": "BTCUSDT",
      "direcao": "up",
      "entrada": 64278.6,
      "stop": 63859.56699,
      "alvo": 64877.7,
      "risco": 419.0330099999992,
      "rr": 1.4,
      "data": "12/06/2026 12:25",
      "status": "loss",
      "resultado": "-1R",
      "order_id": null,
      "tipo": "M1_W_LONG",
      "fechamento": "12/06/2026 12:42"
    },
    {
      "id": 201,
      "symbol": "TONUSDT",
      "direcao": "up",
      "entrada": 1.7469,
      "stop": 1.7204671,
      "alvo": 1.7748,
      "risco": 0.02643289999999987,
      "rr": 1.1,
      "data": "12/06/2026 12:26",
      "status": "loss",
      "resultado": "-1R",
      "order_id": null,
      "tipo": "M1_SWING_LONG",
      "fechamento": "12/06/2026 12:59"
    },
    {
      "id": 201,
      "symbol": "TONUSDT",
      "direcao": "down",
      "entrada": 1.7469,
      "stop": 1.7760423599999997,
      "alvo": 1.6905999999999999,
      "risco": 0.029142359999999812,
      "rr": 1.9,
      "data": "12/06/2026 12:26",
      "status": "aberto",
      "resultado": null,
      "order_id": null,
      "tipo": "M1_M_SHORT"
    },
    {
      "id": 201,
      "symbol": "BNBUSDT",
      "direcao": "up",
      "entrada": 611.54,
      "stop": 607.564407,
      "alvo": 618.27,
      "risco": 3.9755930000000035,
      "rr": 1.7,
      "data": "12/06/2026 12:27",
      "status": "loss",
      "resultado": "-1R",
      "order_id": "a5852e21-f896-4d6b-ae34-f72f407f8a3c",
      "tipo": "M1_W_LONG",
      "fechamento": "12/06/2026 12:57"
    },
    {
      "id": 201,
      "symbol": "BNBUSDT",
      "direcao": "down",
      "entrada": 611.54,
      "stop": 613.5591909999999,
      "alvo": 608.67,
      "risco": 2.019190999999978,
      "rr": 1.4,
      "data": "12/06/2026 12:28",
      "status": "win",
      "resultado": "+1.4R",
      "order_id": "e65e81bb-3cad-4aee-b714-6a4985c48c59",
      "tipo": "M1_M_SHORT",
      "fechamento": "12/06/2026 12:56"
    },
    {
      "id": 201,
      "symbol": "SOLUSDT",
      "direcao": "up",
      "entrada": 68.46,
      "stop": 67.642617,
      "alvo": 69.53,
      "risco": 0.8173829999999924,
      "rr": 1.3,
      "data": "12/06/2026 12:28",
      "status": "loss",
      "resultado": "-1R",
      "order_id": "c8c80b0a-9a5b-454c-a697-5a034484a6a5",
      "tipo": "M1_W_LONG",
      "fechamento": "12/06/2026 12:48"
    },
    {
      "id": 201,
      "symbol": "ETHUSDT",
      "direcao": "up",
      "entrada": 1685.78,
      "stop": 1680.1630619999999,
      "alvo": 1691.9800000000002,
      "risco": 5.616938000000118,
      "rr": 1.1,
      "data": "12/06/2026 12:28",
      "status": "loss",
      "resultado": "-1R",
      "order_id": null,
      "tipo": "M1_W_LONG",
      "fechamento": "12/06/2026 12:32"
    },
    {
      "id": 201,
      "symbol": "ETHUSDT",
      "direcao": "down",
      "entrada": 1685.78,
      "stop": 1691.963546,
      "alvo": 1675.78,
      "risco": 6.1835459999999784,
      "rr": 1.6,
      "data": "12/06/2026 12:28",
      "status": "win",
      "resultado": "+1.6R",
      "order_id": null,
      "tipo": "M1_M_SHORT",
      "fechamento": "12/06/2026 12:35"
    },
    {
      "id": 201,
      "symbol": "BTCUSDT",
      "direcao": "up",
      "entrada": 64281.0,
      "stop": 63859.56699,
      "alvo": 64877.7,
      "risco": 421.43301000000065,
      "rr": 1.4,
      "data": "12/06/2026 12:28",
      "status": "loss",
      "resultado": "-1R",
      "order_id": null,
      "tipo": "M1_W_LONG",
      "fechamento": "12/06/2026 12:42"
    },
    {
      "id": 201,
      "symbol": "SUIUSDT",
      "direcao": "down",
      "entrada": 0.7632,
      "stop": 0.77123949,
      "alvo": 0.7505000000000001,
      "risco": 0.008039490000000038,
      "rr": 1.6,
      "data": "12/06/2026 12:29",
      "status": "win",
      "resultado": "+1.6R",
      "order_id": null,
      "tipo": "M1_M_SHORT",
      "fechamento": "12/06/2026 12:56"
    },
    {
      "id": 201,
      "symbol": "TONUSDT",
      "direcao": "down",
      "entrada": 1.7389,
      "stop": 1.7760423599999997,
      "alvo": 1.6905999999999999,
      "risco": 0.03714235999999982,
      "rr": 1.3,
      "data": "12/06/2026 12:29",
      "status": "aberto",
      "resultado": null,
      "order_id": null,
      "tipo": "M1_M_SHORT"
    },
    {
      "id": 201,
      "symbol": "BNBUSDT",
      "direcao": "up",
      "entrada": 611.96,
      "stop": 607.564407,
      "alvo": 618.27,
      "risco": 4.395593000000076,
      "rr": 1.4,
      "data": "12/06/2026 12:30",
      "status": "loss",
      "resultado": "-1R",
      "order_id": null,
      "tipo": "M1_W_LONG",
      "fechamento": "12/06/2026 12:57"
    },
    {
      "id": 201,
      "symbol": "BTCUSDT",
      "direcao": "up",
      "entrada": 64107.9,
      "stop": 63865.95742,
      "alvo": 64391.0,
      "risco": 241.94258000000264,
      "rr": 1.2,
      "data": "12/06/2026 12:30",
      "status": "loss",
      "resultado": "-1R",
      "order_id": null,
      "tipo": "M1_SWING_LONG",
      "fechamento": "12/06/2026 12:42"
    },
    {
      "id": 201,
      "symbol": "NEARUSDT",
      "direcao": "up",
      "entrada": 2.085,
      "stop": 2.05116856,
      "alvo": 2.1252,
      "risco": 0.03383144000000016,
      "rr": 1.2,
      "data": "12/06/2026 12:31",
      "status": "loss",
      "resultado": "-1R",
      "order_id": null,
      "tipo": "M1_SWING_LONG",
      "fechamento": "12/06/2026 12:49"
    },
    {
      "id": 201,
      "symbol": "NEARUSDT",
      "direcao": "down",
      "entrada": 2.085,
      "stop": 2.1266876399999997,
      "alvo": 2.0268,
      "risco": 0.04168763999999969,
      "rr": 1.4,
      "data": "12/06/2026 12:31",
      "status": "win",
      "resultado": "+1.4R",
      "order_id": null,
      "tipo": "M1_M_SHORT",
      "fechamento": "12/06/2026 13:00"
    },
    {
      "id": 201,
      "symbol": "BTCUSDT",
      "direcao": "down",
      "entrada": 64035.4,
      "stop": 64436.07369999999,
      "alvo": 63417.600000000006,
      "risco": 400.6736999999921,
      "rr": 1.5,
      "data": "12/06/2026 12:32",
      "status": "aberto",
      "resultado": null,
      "order_id": null,
      "tipo": "M1_M_SHORT"
    },
    {
      "id": 201,
      "symbol": "TONUSDT",
      "direcao": "down",
      "entrada": 1.7338,
      "stop": 1.7760423599999997,
      "alvo": 1.6905999999999999,
      "risco": 0.0422423599999997,
      "rr": 1.0,
      "data": "12/06/2026 12:32",
      "status": "aberto",
      "resultado": null,
      "order_id": null,
      "tipo": "M1_M_SHORT"
    },
    {
      "id": 201,
      "symbol": "SUIUSDT",
      "direcao": "down",
      "entrada": 0.762,
      "stop": 0.77123949,
      "alvo": 0.7505000000000001,
      "risco": 0.009239490000000017,
      "rr": 1.2,
      "data": "12/06/2026 12:32",
      "status": "win",
      "resultado": "+1.2R",
      "order_id": null,
      "tipo": "M1_M_SHORT",
      "fechamento": "12/06/2026 12:56"
    },
    {
      "id": 201,
      "symbol": "BNBUSDT",
      "direcao": "up",
      "entrada": 611.96,
      "stop": 607.564407,
      "alvo": 618.27,
      "risco": 4.395593000000076,
      "rr": 1.4,
      "data": "12/06/2026 12:33",
      "status": "loss",
      "resultado": "-1R",
      "order_id": null,
      "tipo": "M1_W_LONG",
      "fechamento": "12/06/2026 12:57"
    },
    {
      "id": 201,
      "symbol": "NEARUSDT",
      "direcao": "up",
      "entrada": 2.0854,
      "stop": 2.05116856,
      "alvo": 2.1252,
      "risco": 0.03423144000000011,
      "rr": 1.2,
      "data": "12/06/2026 12:34",
      "status": "loss",
      "resultado": "-1R",
      "order_id": null,
      "tipo": "M1_SWING_LONG",
      "fechamento": "12/06/2026 12:49"
    },
    {
      "id": 201,
      "symbol": "NEARUSDT",
      "direcao": "down",
      "entrada": 2.0854,
      "stop": 2.1266876399999997,
      "alvo": 2.0268,
      "risco": 0.04128763999999974,
      "rr": 1.4,
      "data": "12/06/2026 12:34",
      "status": "win",
      "resultado": "+1.4R",
      "order_id": null,
      "tipo": "M1_M_SHORT",
      "fechamento": "12/06/2026 13:00"
    },
    {
      "id": 201,
      "symbol": "BTCUSDT",
      "direcao": "up",
      "entrada": 63968.9,
      "stop": 63549.8472,
      "alvo": 64391.0,
      "risco": 419.05280000000494,
      "rr": 1.0,
      "data": "12/06/2026 12:34",
      "status": "loss",
      "resultado": "-1R",
      "order_id": null,
      "tipo": "M1_SWING_LONG",
      "fechamento": "12/06/2026 13:02"
    },
    {
      "id": 201,
      "symbol": "ETHUSDT",
      "direcao": "up",
      "entrada": 1674.6,
      "stop": 1667.24905,
      "alvo": 1686.26,
      "risco": 7.350950000000012,
      "rr": 1.6,
      "data": "12/06/2026 12:35",
      "status": "loss",
      "resultado": "-1R",
      "order_id": null,
      "tipo": "M1_SWING_LONG",
      "fechamento": "12/06/2026 12:49"
    },
    {
      "id": 201,
      "symbol": "ETHUSDT",
      "direcao": "up",
      "entrada": 1674.6,
      "stop": 1661.679592,
      "alvo": 1690.78,
      "risco": 12.920407999999952,
      "rr": 1.3,
      "data": "12/06/2026 12:35",
      "status": "loss",
      "resultado": "-1R",
      "order_id": null,
      "tipo": "EW_ABC_LEG_C_LONG",
      "fechamento": "12/06/2026 13:00"
    },
    {
      "id": 201,
      "symbol": "ETHUSDT",
      "direcao": "up",
      "entrada": 1677.46,
      "stop": 1667.24905,
      "alvo": 1690.78,
      "risco": 10.210950000000139,
      "rr": 1.3,
      "data": "12/06/2026 12:36",
      "status": "loss",
      "resultado": "-1R",
      "order_id": null,
      "tipo": "M1_SWING_LONG",
      "fechamento": "12/06/2026 12:49"
    },
    {
      "id": 201,
      "symbol": "NEARUSDT",
      "direcao": "up",
      "entrada": 2.0864,
      "stop": 2.053767,
      "alvo": 2.1252,
      "risco": 0.03263299999999969,
      "rr": 1.2,
      "data": "12/06/2026 12:36",
      "status": "loss",
      "resultado": "-1R",
      "order_id": null,
      "tipo": "M1_SWING_LONG",
      "fechamento": "12/06/2026 12:49"
    },
    {
      "id": 201,
      "symbol": "NEARUSDT",
      "direcao": "down",
      "entrada": 2.0864,
      "stop": 2.1266876399999997,
      "alvo": 2.0268,
      "risco": 0.04028763999999985,
      "rr": 1.5,
      "data": "12/06/2026 12:36",
      "status": "win",
      "resultado": "+1.5R",
      "order_id": null,
      "tipo": "M1_M_SHORT",
      "fechamento": "12/06/2026 13:00"
    },
    {
      "id": 201,
      "symbol": "BTCUSDT",
      "direcao": "up",
      "entrada": 64052.6,
      "stop": 63865.95742,
      "alvo": 64301.4,
      "risco": 186.64257999999973,
      "rr": 1.3,
      "data": "12/06/2026 12:37",
      "status": "loss",
      "resultado": "-1R",
      "order_id": null,
      "tipo": "M1_SWING_LONG",
      "fechamento": "12/06/2026 12:42"
    },
    {
      "id": 201,
      "symbol": "ETHUSDT",
      "direcao": "up",
      "entrada": 1675.44,
      "stop": 1661.679592,
      "alvo": 1690.78,
      "risco": 13.760408000000098,
      "rr": 1.1,
      "data": "12/06/2026 12:38",
      "status": "loss",
      "resultado": "-1R",
      "order_id": "2283acf6-8fe9-428e-9134-054eb0bd6b9b",
      "tipo": "EW_ABC_LEG_C_LONG",
      "fechamento": "12/06/2026 13:00"
    },
    {
      "id": 201,
      "symbol": "BTCUSDT",
      "direcao": "up",
      "entrada": 63911.6,
      "stop": 63549.8472,
      "alvo": 64301.4,
      "risco": 361.752800000002,
      "rr": 1.1,
      "data": "12/06/2026 12:39",
      "status": "loss",
      "resultado": "-1R",
      "order_id": null,
      "tipo": "M1_SWING_LONG",
      "fechamento": "12/06/2026 13:02"
    },
    {
      "id": 201,
      "symbol": "ETHUSDT",
      "direcao": "down",
      "entrada": 1672.86,
      "stop": 1687.4403819999998,
      "alvo": 1657.74,
      "risco": 14.580381999999872,
      "rr": 1.0,
      "data": "12/06/2026 12:40",
      "status": "aberto",
      "resultado": null,
      "order_id": "40d3bf09-2c08-49a4-b2d1-6f55128d071d",
      "tipo": "M1_M_SHORT"
    },
    {
      "id": 201,
      "symbol": "ETHUSDT",
      "direcao": "up",
      "entrada": 1672.86,
      "stop": 1661.679592,
      "alvo": 1690.78,
      "risco": 11.180407999999943,
      "rr": 1.6,
      "data": "12/06/2026 12:40",
      "status": "loss",
      "resultado": "-1R",
      "order_id": "49759368-7326-48b4-a8af-3673dfc3bea3",
      "tipo": "EW_ABC_LEG_C_LONG",
      "fechamento": "12/06/2026 13:00"
    },
    {
      "id": 201,
      "symbol": "BTCUSDT",
      "direcao": "up",
      "entrada": 63856.1,
      "stop": 63549.8472,
      "alvo": 64301.4,
      "risco": 306.252800000002,
      "rr": 1.5,
      "data": "12/06/2026 12:41",
      "status": "loss",
      "resultado": "-1R",
      "order_id": null,
      "tipo": "M1_SWING_LONG",
      "fechamento": "12/06/2026 13:02"
    },
    {
      "id": 201,
      "symbol": "NEARUSDT",
      "direcao": "up",
      "entrada": 2.0578,
      "stop": 2.0433686399999997,
      "alvo": 2.0733,
      "risco": 0.014431360000000115,
      "rr": 1.1,
      "data": "12/06/2026 12:43",
      "status": "loss",
      "resultado": "-1R",
      "order_id": null,
      "tipo": "M1_PULLBACK_LONG",
      "fechamento": "12/06/2026 13:00"
    },
    {
      "id": 201,
      "symbol": "SOLUSDT",
      "direcao": "up",
      "entrada": 67.72,
      "stop": 67.10971,
      "alvo": 68.46,
      "risco": 0.610289999999992,
      "rr": 1.2,
      "data": "12/06/2026 12:43",
      "status": "aberto",
      "resultado": null,
      "order_id": "02b8723a-0de5-4349-bb08-80cb35e9ed60",
      "tipo": "M1_SWING_LONG"
    },
    {
      "id": 201,
      "symbol": "BNBUSDT",
      "direcao": "down",
      "entrada": 609.05,
      "stop": 612.388372,
      "alvo": 605.54,
      "risco": 3.3383720000000494,
      "rr": 1.1,
      "data": "12/06/2026 12:45",
      "status": "aberto",
      "resultado": null,
      "order_id": null,
      "tipo": "M1_M_SHORT"
    },
    {
      "id": 201,
      "symbol": "SOLUSDT",
      "direcao": "up",
      "entrada": 67.75,
      "stop": 67.10971,
      "alvo": 68.46,
      "risco": 0.6402899999999931,
      "rr": 1.1,
      "data": "12/06/2026 12:45",
      "status": "aberto",
      "resultado": null,
      "order_id": "742764a8-64a3-43ad-8510-9fe15a53f7fe",
      "tipo": "M1_SWING_LONG"
    },
    {
      "id": 201,
      "symbol": "BTCUSDT",
      "direcao": "up",
      "entrada": 63879.8,
      "stop": 63460.30096,
      "alvo": 64301.4,
      "risco": 419.4990400000024,
      "rr": 1.0,
      "data": "12/06/2026 12:46",
      "status": "aberto",
      "resultado": null,
      "order_id": null,
      "tipo": "M1_SWING_LONG"
    },
    {
      "id": 201,
      "symbol": "SOLUSDT",
      "direcao": "up",
      "entrada": 67.59,
      "stop": 67.10971,
      "alvo": 68.23,
      "risco": 0.48028999999999655,
      "rr": 1.3,
      "data": "12/06/2026 12:48",
      "status": "aberto",
      "resultado": null,
      "order_id": null,
      "tipo": "M1_SWING_LONG"
    },
    {
      "id": 201,
      "symbol": "NEARUSDT",
      "direcao": "down",
      "entrada": 2.0538,
      "stop": 2.0955658699999997,
      "alvo": 1.9954999999999998,
      "risco": 0.04176586999999987,
      "rr": 1.4,
      "data": "12/06/2026 12:48",
      "status": "aberto",
      "resultado": null,
      "order_id": null,
      "tipo": "M1_M_SHORT"
    },
    {
      "id": 201,
      "symbol": "BTCUSDT",
      "direcao": "up",
      "entrada": 63801.9,
      "stop": 63291.62616,
      "alvo": 64391.0,
      "risco": 510.27384000000166,
      "rr": 1.2,
      "data": "12/06/2026 12:48",
      "status": "aberto",
      "resultado": null,
      "order_id": null,
      "tipo": "EW_ABC_LEG_C_LONG"
    },
    {
      "id": 201,
      "symbol": "BNBUSDT",
      "direcao": "down",
      "entrada": 609.05,
      "stop": 612.388372,
      "alvo": 605.54,
      "risco": 3.3383720000000494,
      "rr": 1.1,
      "data": "12/06/2026 12:48",
      "status": "aberto",
      "resultado": null,
      "order_id": null,
      "tipo": "M1_M_SHORT"
    },
    {
      "id": 201,
      "symbol": "BTCUSDT",
      "direcao": "up",
      "entrada": 63710.9,
      "stop": 63460.30096,
      "alvo": 64062.5,
      "risco": 250.59904000000097,
      "rr": 1.4,
      "data": "12/06/2026 12:49",
      "status": "aberto",
      "resultado": null,
      "order_id": null,
      "tipo": "M1_SWING_LONG"
    },
    {
      "id": 201,
      "symbol": "BNBUSDT",
      "direcao": "down",
      "entrada": 609.05,
      "stop": 612.388372,
      "alvo": 605.54,
      "risco": 3.3383720000000494,
      "rr": 1.1,
      "data": "12/06/2026 12:51",
      "status": "aberto",
      "resultado": null,
      "order_id": "3d132c6f-4442-4741-8a22-dafdf5ea661a",
      "tipo": "M1_M_SHORT"
    },
    {
      "id": 201,
      "symbol": "NEARUSDT",
      "direcao": "down",
      "entrada": 2.0559,
      "stop": 2.0955658699999997,
      "alvo": 1.9954999999999998,
      "risco": 0.03966586999999988,
      "rr": 1.5,
      "data": "12/06/2026 12:51",
      "status": "aberto",
      "resultado": null,
      "order_id": null,
      "tipo": "M1_M_SHORT"
    },
    {
      "id": 201,
      "symbol": "BTCUSDT",
      "direcao": "up",
      "entrada": 63764.1,
      "stop": 63291.62616,
      "alvo": 64391.0,
      "risco": 472.47383999999875,
      "rr": 1.3,
      "data": "12/06/2026 12:51",
      "status": "aberto",
      "resultado": null,
      "order_id": null,
      "tipo": "EW_ABC_LEG_C_LONG"
    },
    {
      "id": 201,
      "symbol": "BNBUSDT",
      "direcao": "down",
      "entrada": 609.05,
      "stop": 612.388372,
      "alvo": 605.54,
      "risco": 3.3383720000000494,
      "rr": 1.1,
      "data": "12/06/2026 12:53",
      "status": "aberto",
      "resultado": null,
      "order_id": null,
      "tipo": "M1_M_SHORT"
    },
    {
      "id": 201,
      "symbol": "NEARUSDT",
      "direcao": "down",
      "entrada": 2.0586,
      "stop": 2.0955658699999997,
      "alvo": 1.9954999999999998,
      "risco": 0.03696586999999951,
      "rr": 1.7,
      "data": "12/06/2026 12:53",
      "status": "aberto",
      "resultado": null,
      "order_id": null,
      "tipo": "M1_M_SHORT"
    },
    {
      "id": 201,
      "symbol": "BTCUSDT",
      "direcao": "up",
      "entrada": 63835.5,
      "stop": 63291.62616,
      "alvo": 64391.0,
      "risco": 543.8738400000002,
      "rr": 1.0,
      "data": "12/06/2026 12:53",
      "status": "aberto",
      "resultado": null,
      "order_id": null,
      "tipo": "EW_ABC_LEG_C_LONG"
    },
    {
      "id": 201,
      "symbol": "BTCUSDT",
      "direcao": "down",
      "entrada": 63847.9,
      "stop": 63973.461059999994,
      "alvo": 63710.2,
      "risco": 125.56105999999272,
      "rr": 1.1,
      "data": "12/06/2026 12:54",
      "status": "win",
      "resultado": "+1.1R",
      "order_id": null,
      "tipo": "M1_SWING_SHORT",
      "fechamento": "12/06/2026 12:59"
    },
    {
      "id": 201,
      "symbol": "SOLUSDT",
      "direcao": "up",
      "entrada": 67.56,
      "stop": 67.119704,
      "alvo": 68.23,
      "risco": 0.4402960000000036,
      "rr": 1.5,
      "data": "12/06/2026 12:56",
      "status": "aberto",
      "resultado": null,
      "order_id": null,
      "tipo": "M1_SWING_LONG"
    },
    {
      "id": 201,
      "symbol": "BTCUSDT",
      "direcao": "up",
      "entrada": 63784.3,
      "stop": 63291.62616,
      "alvo": 64391.0,
      "risco": 492.6738400000031,
      "rr": 1.2,
      "data": "12/06/2026 12:56",
      "status": "aberto",
      "resultado": null,
      "order_id": null,
      "tipo": "EW_ABC_LEG_C_LONG"
    },
    {
      "id": 201,
      "symbol": "NEARUSDT",
      "direcao": "down",
      "entrada": 2.0526,
      "stop": 2.0955658699999997,
      "alvo": 1.9954999999999998,
      "risco": 0.04296586999999974,
      "rr": 1.3,
      "data": "12/06/2026 12:56",
      "status": "aberto",
      "resultado": null,
      "order_id": null,
      "tipo": "M1_M_SHORT"
    },
    {
      "id": 201,
      "symbol": "ETHUSDT",
      "direcao": "up",
      "entrada": 1663.82,
      "stop": 1661.845893,
      "alvo": 1668.88,
      "risco": 1.9741070000000036,
      "rr": 2.6,
      "data": "12/06/2026 12:57",
      "status": "loss",
      "resultado": "-1R",
      "order_id": "d9c0d258-916f-449d-ae90-8b1d1579db5c",
      "tipo": "EW_W2_LONG",
      "fechamento": "12/06/2026 13:00"
    },
    {
      "id": 201,
      "symbol": "BTCUSDT",
      "direcao": "up",
      "entrada": 63672.1,
      "stop": 63439.313559999995,
      "alvo": 63935.1,
      "risco": 232.7864400000035,
      "rr": 1.1,
      "data": "12/06/2026 12:58",
      "status": "aberto",
      "resultado": null,
      "order_id": null,
      "tipo": "M1_SWING_LONG"
    },
    {
      "id": 201,
      "symbol": "NEARUSDT",
      "direcao": "down",
      "entrada": 2.0465,
      "stop": 2.0955658699999997,
      "alvo": 1.9954999999999998,
      "risco": 0.049065869999999734,
      "rr": 1.0,
      "data": "12/06/2026 12:59",
      "status": "aberto",
      "resultado": null,
      "order_id": null,
      "tipo": "M1_M_SHORT"
    },
    {
      "id": 201,
      "symbol": "BTCUSDT",
      "direcao": "up",
      "entrada": 63643.1,
      "stop": 63439.313559999995,
      "alvo": 63935.1,
      "risco": 203.7864400000035,
      "rr": 1.4,
      "data": "12/06/2026 13:01",
      "status": "aberto",
      "resultado": null,
      "order_id": null,
      "tipo": "M1_SWING_LONG"
    },
    {
      "id": 201,
      "symbol": "BTCUSDT",
      "direcao": "up",
      "entrada": 63628.0,
      "stop": 63439.313559999995,
      "alvo": 63848.7,
      "risco": 188.68644000000495,
      "rr": 1.2,
      "data": "12/06/2026 13:04",
      "status": "aberto",
      "resultado": null,
      "order_id": null,
      "tipo": "M1_SWING_LONG"
    }
  ],
  "zone_tol": 0.08,
  "min_wave_usd": 30,
  "total_prints": 20,
  "last_update": "11/06/2026 21:46",
  "manual_trades": [
    {
      "id": 1,
      "symbol": "ETHUSDT",
      "side": "Sell",
      "size": 0.01,
      "entrada": 1594.95,
      "pnl_usd": 0.0465,
      "data": "06/06/2026 01:00",
      "status": "fechado",
      "origem": "manual",
      "fechamento": "06/06/2026 01:13"
    },
    {
      "id": 2,
      "symbol": "BTCUSDT",
      "side": "Sell",
      "size": 0.001,
      "entrada": 63243.4,
      "pnl_usd": 2.13695,
      "data": "06/06/2026 01:01",
      "status": "aberto",
      "origem": "manual"
    }
  ]
}